{
"meta":{"test_sets":[],"test_metrics":[],"learn_metrics":[{"best_value":"Min","name":"Logloss"}],"launch_mode":"Train","parameters":"","iteration_count":1000,"learn_sets":["learn"],"name":"experiment"},
"iterations":[
{"learn":[0.6849545746],"iteration":0,"passed_time":0.168633993,"remaining_time":168.465359},
{"learn":[0.678187532],"iteration":1,"passed_time":0.1817111202,"remaining_time":90.67384899},
{"learn":[0.6719043801],"iteration":2,"passed_time":0.1945188675,"remaining_time":64.64510364},
{"learn":[0.6666009983],"iteration":3,"passed_time":0.2079343408,"remaining_time":51.77565085},
{"learn":[0.6616183639],"iteration":4,"passed_time":0.2382431879,"remaining_time":47.41039439},
{"learn":[0.657260481],"iteration":5,"passed_time":0.2560055634,"remaining_time":42.41158833},
{"learn":[0.6532589589],"iteration":6,"passed_time":0.2707698372,"remaining_time":38.41063547},
{"learn":[0.6496787453],"iteration":7,"passed_time":0.2843784193,"remaining_time":35.26292399},
{"learn":[0.646317444],"iteration":8,"passed_time":0.2983633213,"remaining_time":32.85311682},
{"learn":[0.6439414065],"iteration":9,"passed_time":0.3119601072,"remaining_time":30.88405061},
{"learn":[0.64144695],"iteration":10,"passed_time":0.3244583184,"remaining_time":29.17175245},
{"learn":[0.6392576578],"iteration":11,"passed_time":0.3380206494,"remaining_time":27.8303668},
{"learn":[0.6373008361],"iteration":12,"passed_time":0.3679260434,"remaining_time":27.93407729},
{"learn":[0.6358796929],"iteration":13,"passed_time":0.3887029936,"remaining_time":27.37579655},
{"learn":[0.6345616361],"iteration":14,"passed_time":0.4020204204,"remaining_time":26.39934094},
{"learn":[0.6331618313],"iteration":15,"passed_time":0.4158966813,"remaining_time":25.5776459},
{"learn":[0.6317480473],"iteration":16,"passed_time":0.4286682641,"remaining_time":24.78711198},
{"learn":[0.6303314425],"iteration":17,"passed_time":0.4423897192,"remaining_time":24.1348169},
{"learn":[0.6292658638],"iteration":18,"passed_time":0.4554932869,"remaining_time":23.5178376},
{"learn":[0.6283162814],"iteration":19,"passed_time":0.4695501098,"remaining_time":23.00795538},
{"learn":[0.6272758743],"iteration":20,"passed_time":0.4839204822,"remaining_time":22.55991201},
{"learn":[0.6263956645],"iteration":21,"passed_time":0.4976715324,"remaining_time":22.12376176},
{"learn":[0.6253771531],"iteration":22,"passed_time":0.5125470133,"remaining_time":21.77210574},
{"learn":[0.6242482302],"iteration":23,"passed_time":0.5268136767,"remaining_time":21.42375619},
{"learn":[0.6233624015],"iteration":24,"passed_time":0.5413434252,"remaining_time":21.11239358},
{"learn":[0.6226368384],"iteration":25,"passed_time":0.5562951696,"remaining_time":20.83967289},
{"learn":[0.6215988654],"iteration":26,"passed_time":0.569476162,"remaining_time":20.52223354},
{"learn":[0.6211240173],"iteration":27,"passed_time":0.5829327428,"remaining_time":20.23609378},
{"learn":[0.620420259],"iteration":28,"passed_time":0.5979823682,"remaining_time":20.02209929},
{"learn":[0.6200236101],"iteration":29,"passed_time":0.6171889206,"remaining_time":19.9557751},
{"learn":[0.61961131],"iteration":30,"passed_time":0.6332416453,"remaining_time":19.7939082},
{"learn":[0.6188900806],"iteration":31,"passed_time":0.6495534701,"remaining_time":19.64899247},
{"learn":[0.6183548343],"iteration":32,"passed_time":0.6638906194,"remaining_time":19.45400694},
{"learn":[0.6178577834],"iteration":33,"passed_time":0.6765734674,"remaining_time":19.22264616},
{"learn":[0.6175014568],"iteration":34,"passed_time":0.6941592281,"remaining_time":19.13896157},
{"learn":[0.6169735357],"iteration":35,"passed_time":0.7100757577,"remaining_time":19.01425085},
{"learn":[0.6162192977],"iteration":36,"passed_time":0.7286843031,"remaining_time":18.96548605},
{"learn":[0.6158505048],"iteration":37,"passed_time":0.7449125409,"remaining_time":18.85804906},
{"learn":[0.6153786937],"iteration":38,"passed_time":0.7639367538,"remaining_time":18.82418514},
{"learn":[0.6150629283],"iteration":39,"passed_time":0.7827079515,"remaining_time":18.78499084},
{"learn":[0.614407898],"iteration":40,"passed_time":0.8005988611,"remaining_time":18.72620263},
{"learn":[0.6138965608],"iteration":41,"passed_time":0.8214192076,"remaining_time":18.73618097},
{"learn":[0.6135034721],"iteration":42,"passed_time":0.8445937595,"remaining_time":18.79712158},
{"learn":[0.613259104],"iteration":43,"passed_time":0.8642696346,"remaining_time":18.77822206},
{"learn":[0.6128278314],"iteration":44,"passed_time":0.8807081395,"remaining_time":18.69058385},
{"learn":[0.6123276297],"iteration":45,"passed_time":0.8997730148,"remaining_time":18.66050992},
{"learn":[0.6119383742],"iteration":46,"passed_time":0.9301905317,"remaining_time":18.86109738},
{"learn":[0.6116256003],"iteration":47,"passed_time":0.9443474372,"remaining_time":18.7295575},
{"learn":[0.6113397838],"iteration":48,"passed_time":0.9580393434,"remaining_time":18.59378399},
{"learn":[0.610846839],"iteration":49,"passed_time":0.9746337591,"remaining_time":18.51804142},
{"learn":[0.6106430094],"iteration":50,"passed_time":0.9922870232,"remaining_time":18.46432128},
{"learn":[0.6102376476],"iteration":51,"passed_time":1.008356005,"remaining_time":18.38310563},
{"learn":[0.6100334426],"iteration":52,"passed_time":1.024841351,"remaining_time":18.31178791},
{"learn":[0.6097428034],"iteration":53,"passed_time":1.041004146,"remaining_time":18.23685042},
{"learn":[0.6095158154],"iteration":54,"passed_time":1.05475172,"remaining_time":18.12255229},
{"learn":[0.6092553297],"iteration":55,"passed_time":1.0736414,"remaining_time":18.09852645},
{"learn":[0.608886059],"iteration":56,"passed_time":1.086461166,"remaining_time":17.97426104},
{"learn":[0.6086701497],"iteration":57,"passed_time":1.10386365,"remaining_time":17.92826825},
{"learn":[0.6083562498],"iteration":58,"passed_time":1.120565156,"remaining_time":17.87206461},
{"learn":[0.6080187479],"iteration":59,"passed_time":1.136188074,"remaining_time":17.80027983},
{"learn":[0.6077996424],"iteration":60,"passed_time":1.154425216,"remaining_time":17.77057832},
{"learn":[0.6075964383],"iteration":61,"passed_time":1.166891828,"remaining_time":17.6539441},
{"learn":[0.6073497157],"iteration":62,"passed_time":1.18294422,"remaining_time":17.59394816},
{"learn":[0.6071782803],"iteration":63,"passed_time":1.199556186,"remaining_time":17.54350922},
{"learn":[0.6068467842],"iteration":64,"passed_time":1.215648492,"remaining_time":17.48663599},
{"learn":[0.6065125695],"iteration":65,"passed_time":1.228807181,"remaining_time":17.38948343},
{"learn":[0.6063697067],"iteration":66,"passed_time":1.247732475,"remaining_time":17.37514029},
{"learn":[0.6061879093],"iteration":67,"passed_time":1.263992945,"remaining_time":17.3241386},
{"learn":[0.6059703848],"iteration":68,"passed_time":1.276622974,"remaining_time":17.22515926},
{"learn":[0.6058047732],"iteration":69,"passed_time":1.294165127,"remaining_time":17.19390811},
{"learn":[0.6055331179],"iteration":70,"passed_time":1.309763579,"remaining_time":17.13761077},
{"learn":[0.6053080408],"iteration":71,"passed_time":1.325021406,"remaining_time":17.07805368},
{"learn":[0.6050972045],"iteration":72,"passed_time":1.339361471,"remaining_time":17.00805594},
{"learn":[0.6048055074],"iteration":73,"passed_time":1.357364819,"remaining_time":16.98540301},
{"learn":[0.6045567032],"iteration":74,"passed_time":1.371426993,"remaining_time":16.91426625},
{"learn":[0.6043306024],"iteration":75,"passed_time":1.385303269,"remaining_time":16.84237133},
{"learn":[0.6042184165],"iteration":76,"passed_time":1.398815926,"remaining_time":16.76762467},
{"learn":[0.6040520656],"iteration":77,"passed_time":1.417568261,"remaining_time":16.7563838},
{"learn":[0.6038483041],"iteration":78,"passed_time":1.432522163,"remaining_time":16.70066978},
{"learn":[0.6035805616],"iteration":79,"passed_time":1.449140747,"remaining_time":16.66511859},
{"learn":[0.60341015],"iteration":80,"passed_time":1.464024767,"remaining_time":16.61035508},
{"learn":[0.6031703544],"iteration":81,"passed_time":1.480344006,"remaining_time":16.57263168},
{"learn":[0.6029782859],"iteration":82,"passed_time":1.494221823,"remaining_time":16.50845074},
{"learn":[0.602827916],"iteration":83,"passed_time":1.511898857,"remaining_time":16.48689706},
{"learn":[0.6026252124],"iteration":84,"passed_time":1.526655128,"remaining_time":16.43399344},
{"learn":[0.6024736482],"iteration":85,"passed_time":1.543647947,"remaining_time":16.40574679},
{"learn":[0.6023220385],"iteration":86,"passed_time":1.563617107,"remaining_time":16.40899332},
{"learn":[0.6021537084],"iteration":87,"passed_time":1.583831425,"remaining_time":16.41425295},
{"learn":[0.6019826598],"iteration":88,"passed_time":1.603022095,"remaining_time":16.40846212},
{"learn":[0.6017308301],"iteration":89,"passed_time":1.619508308,"remaining_time":16.37502844},
{"learn":[0.6015912204],"iteration":90,"passed_time":1.638082488,"remaining_time":16.36282397},
{"learn":[0.6014643274],"iteration":91,"passed_time":1.657539736,"remaining_time":16.35919652},
{"learn":[0.6013405622],"iteration":92,"passed_time":1.676191887,"remaining_time":16.34737679},
{"learn":[0.6011586397],"iteration":93,"passed_time":1.693405832,"remaining_time":16.32154983},
{"learn":[0.6010043798],"iteration":94,"passed_time":1.713898798,"remaining_time":16.32714118},
{"learn":[0.6008413502],"iteration":95,"passed_time":1.732744255,"remaining_time":16.31667507},
{"learn":[0.6007167775],"iteration":96,"passed_time":1.752681006,"remaining_time":16.31619535},
{"learn":[0.6005723109],"iteration":97,"passed_time":1.772139888,"remaining_time":16.31092019},
{"learn":[0.6004263771],"iteration":98,"passed_time":1.790894075,"remaining_time":16.29894507},
{"learn":[0.6003322424],"iteration":99,"passed_time":1.808819519,"remaining_time":16.27937567},
{"learn":[0.6001598857],"iteration":100,"passed_time":1.824202413,"remaining_time":16.23720761},
{"learn":[0.600053569],"iteration":101,"passed_time":1.838666501,"remaining_time":16.18747566},
{"learn":[0.5999502665],"iteration":102,"passed_time":1.853513019,"remaining_time":16.14175901},
{"learn":[0.5998139668],"iteration":103,"passed_time":1.86623635,"remaining_time":16.07834393},
{"learn":[0.5996833315],"iteration":104,"passed_time":1.881687178,"remaining_time":16.03914309},
{"learn":[0.5995679493],"iteration":105,"passed_time":1.896177025,"remaining_time":15.99228547},
{"learn":[0.599476772],"iteration":106,"passed_time":1.911366363,"remaining_time":15.95187068},
{"learn":[0.5993505045],"iteration":107,"passed_time":1.924925529,"remaining_time":15.898459},
{"learn":[0.5991935261],"iteration":108,"passed_time":1.938094554,"remaining_time":15.84258943},
{"learn":[0.5990906558],"iteration":109,"passed_time":1.950910582,"remaining_time":15.78464017},
{"learn":[0.5989507959],"iteration":110,"passed_time":1.965061458,"remaining_time":15.73819492},
{"learn":[0.5988257113],"iteration":111,"passed_time":1.97896057,"remaining_time":15.69033024},
{"learn":[0.598740642],"iteration":112,"passed_time":1.993382707,"remaining_time":15.64717222},
{"learn":[0.5986407177],"iteration":113,"passed_time":2.007252358,"remaining_time":15.60022447},
{"learn":[0.5984398227],"iteration":114,"passed_time":2.020879299,"remaining_time":15.55198417},
{"learn":[0.5983002357],"iteration":115,"passed_time":2.037822078,"remaining_time":15.52960963},
{"learn":[0.59821561],"iteration":116,"passed_time":2.051851455,"remaining_time":15.48534047},
{"learn":[0.5980250088],"iteration":117,"passed_time":2.065107527,"remaining_time":15.43580372},
{"learn":[0.5979106845],"iteration":118,"passed_time":2.079134565,"remaining_time":15.39258447},
{"learn":[0.5978114881],"iteration":119,"passed_time":2.093153482,"remaining_time":15.3497922},
{"learn":[0.5976623012],"iteration":120,"passed_time":2.1071384,"remaining_time":15.30722854},
{"learn":[0.5975547105],"iteration":121,"passed_time":2.12103465,"remaining_time":15.26449527},
{"learn":[0.5974225397],"iteration":122,"passed_time":2.135598754,"remaining_time":15.22699274},
{"learn":[0.597318623],"iteration":123,"passed_time":2.149733926,"remaining_time":15.18683},
{"learn":[0.597229948],"iteration":124,"passed_time":2.1636362,"remaining_time":15.1454534},
{"learn":[0.5970765411],"iteration":125,"passed_time":2.176757306,"remaining_time":15.09909433},
{"learn":[0.5969700879],"iteration":126,"passed_time":2.190495351,"remaining_time":15.05749954},
{"learn":[0.596839282],"iteration":127,"passed_time":2.203687644,"remaining_time":15.01262207},
{"learn":[0.5967402677],"iteration":128,"passed_time":2.217516729,"remaining_time":14.97253544},
{"learn":[0.5965657158],"iteration":129,"passed_time":2.231855489,"remaining_time":14.93626366},
{"learn":[0.5964422123],"iteration":130,"passed_time":2.245792319,"remaining_time":14.8976605},
{"learn":[0.5963340301],"iteration":131,"passed_time":2.259584872,"remaining_time":14.85848234},
{"learn":[0.5962674215],"iteration":132,"passed_time":2.273395666,"remaining_time":14.81980483},
{"learn":[0.5961462384],"iteration":133,"passed_time":2.286112915,"remaining_time":14.77443122},
{"learn":[0.5960495899],"iteration":134,"passed_time":2.299547419,"remaining_time":14.73413716},
{"learn":[0.5959427045],"iteration":135,"passed_time":2.313849481,"remaining_time":14.69974965},
{"learn":[0.5958427915],"iteration":136,"passed_time":2.327709082,"remaining_time":14.66286816},
{"learn":[0.5957662303],"iteration":137,"passed_time":2.34106786,"remaining_time":14.62319199},
{"learn":[0.5956866321],"iteration":138,"passed_time":2.355137613,"remaining_time":14.58829845},
{"learn":[0.5955323039],"iteration":139,"passed_time":2.369073382,"remaining_time":14.55287934},
{"learn":[0.5954412403],"iteration":140,"passed_time":2.382106542,"remaining_time":14.5122661},
{"learn":[0.5953141993],"iteration":141,"passed_time":2.396511331,"remaining_time":14.48032903},
{"learn":[0.5952191092],"iteration":142,"passed_time":2.410806819,"remaining_time":14.44798212},
{"learn":[0.5950689099],"iteration":143,"passed_time":2.424827838,"remaining_time":14.41425437},
{"learn":[0.59500047],"iteration":144,"passed_time":2.439307449,"remaining_time":14.38350254},
{"learn":[0.5949436206],"iteration":145,"passed_time":2.452773562,"remaining_time":14.34704536},
{"learn":[0.5948418082],"iteration":146,"passed_time":2.467513795,"remaining_time":14.31829434},
{"learn":[0.5947278706],"iteration":147,"passed_time":2.480991506,"remaining_time":14.28246462},
{"learn":[0.5946529927],"iteration":148,"passed_time":2.494950557,"remaining_time":14.24968405},
{"learn":[0.5945454362],"iteration":149,"passed_time":2.510968258,"remaining_time":14.22882013},
{"learn":[0.5944162114],"iteration":150,"passed_time":2.530442325,"remaining_time":14.22745387},
{"learn":[0.5943187098],"iteration":151,"passed_time":2.549274722,"remaining_time":14.2222695},
{"learn":[0.5942320594],"iteration":152,"passed_time":2.566722881,"remaining_time":14.20924366},
{"learn":[0.5940896289],"iteration":153,"passed_time":2.584955242,"remaining_time":14.20046841},
{"learn":[0.5939228799],"iteration":154,"passed_time":2.603061739,"remaining_time":14.19088496},
{"learn":[0.5938273688],"iteration":155,"passed_time":2.619932077,"remaining_time":14.17450431},
{"learn":[0.5937338142],"iteration":156,"passed_time":2.638773824,"remaining_time":14.16870276},
{"learn":[0.5936254501],"iteration":157,"passed_time":2.656373119,"remaining_time":14.15611498},
{"learn":[0.5935393571],"iteration":158,"passed_time":2.674093162,"remaining_time":14.14410283},
{"learn":[0.5934554138],"iteration":159,"passed_time":2.689776505,"remaining_time":14.12132665},
{"learn":[0.5933966877],"iteration":160,"passed_time":2.709243142,"remaining_time":14.11835401},
{"learn":[0.5933173511],"iteration":161,"passed_time":2.726311573,"remaining_time":14.10277221},
{"learn":[0.5931655253],"iteration":162,"passed_time":2.743386493,"remaining_time":14.08720549},
{"learn":[0.5930108445],"iteration":163,"passed_time":2.76310557,"remaining_time":14.08509913},
{"learn":[0.5929101694],"iteration":164,"passed_time":2.784236531,"remaining_time":14.08992426},
{"learn":[0.5927514394],"iteration":165,"passed_time":2.801568085,"remaining_time":14.07534809},
{"learn":[0.5926426203],"iteration":166,"passed_time":2.815913033,"remaining_time":14.04584165},
{"learn":[0.5925513178],"iteration":167,"passed_time":2.8320415,"remaining_time":14.02534838},
{"learn":[0.5924471508],"iteration":168,"passed_time":2.849167866,"remaining_time":14.00981359},
{"learn":[0.5923627071],"iteration":169,"passed_time":2.866229729,"remaining_time":13.99394515},
{"learn":[0.5922275675],"iteration":170,"passed_time":2.882124281,"remaining_time":13.97240368},
{"learn":[0.5921126859],"iteration":171,"passed_time":2.8992248,"remaining_time":13.95673334},
{"learn":[0.5919995217],"iteration":172,"passed_time":2.912858762,"remaining_time":13.92447512},
{"learn":[0.5919242572],"iteration":173,"passed_time":2.929200875,"remaining_time":13.90528691},
{"learn":[0.5918610722],"iteration":174,"passed_time":2.947712687,"remaining_time":13.89635981},
{"learn":[0.591705254],"iteration":175,"passed_time":2.963385074,"remaining_time":13.87403012},
{"learn":[0.5915831041],"iteration":176,"passed_time":2.980128147,"remaining_time":13.85675404},
{"learn":[0.5914541977],"iteration":177,"passed_time":2.994179047,"remaining_time":13.82705155},
{"learn":[0.5913744289],"iteration":178,"passed_time":3.01144673,"remaining_time":13.81227802},
{"learn":[0.5912374126],"iteration":179,"passed_time":3.028697964,"remaining_time":13.79740183},
{"learn":[0.5911308911],"iteration":180,"passed_time":3.044342876,"remaining_time":13.77523103},
{"learn":[0.5910328777],"iteration":181,"passed_time":3.057633559,"remaining_time":13.74255083},
{"learn":[0.590874887],"iteration":182,"passed_time":3.076385802,"remaining_time":13.73446558},
{"learn":[0.590768229],"iteration":183,"passed_time":3.092011836,"remaining_time":13.71240031},
{"learn":[0.5906401758],"iteration":184,"passed_time":3.105647467,"remaining_time":13.68163614},
{"learn":[0.5905434363],"iteration":185,"passed_time":3.121042293,"remaining_time":13.65875498},
{"learn":[0.5904707082],"iteration":186,"passed_time":3.138379177,"remaining_time":13.64439717},
{"learn":[0.5903538246],"iteration":187,"passed_time":3.152554646,"remaining_time":13.61635305},
{"learn":[0.5902190377],"iteration":188,"passed_time":3.167141147,"remaining_time":13.59021942},
{"learn":[0.5900884366],"iteration":189,"passed_time":3.184859959,"remaining_time":13.57756088},
{"learn":[0.5899870222],"iteration":190,"passed_time":3.202206825,"remaining_time":13.56327393},
{"learn":[0.5898651567],"iteration":191,"passed_time":3.2156973,"remaining_time":13.53272614},
{"learn":[0.5897905859],"iteration":192,"passed_time":3.230837468,"remaining_time":13.50925304},
{"learn":[0.5896834503],"iteration":193,"passed_time":3.24879328,"remaining_time":13.49756384},
{"learn":[0.5895085002],"iteration":194,"passed_time":3.264724516,"remaining_time":13.47745249},
{"learn":[0.5894220091],"iteration":195,"passed_time":3.27988135,"remaining_time":13.45420717},
{"learn":[0.5893257474],"iteration":196,"passed_time":3.294622915,"remaining_time":13.42935127},
{"learn":[0.5892490951],"iteration":197,"passed_time":3.31100714,"remaining_time":13.41125114},
{"learn":[0.5891470666],"iteration":198,"passed_time":3.326657796,"remaining_time":13.39021555},
{"learn":[0.5889589905],"iteration":199,"passed_time":3.341716685,"remaining_time":13.36686674},
{"learn":[0.5888284007],"iteration":200,"passed_time":3.359341556,"remaining_time":13.35380051},
{"learn":[0.5887521921],"iteration":201,"passed_time":3.375492672,"remaining_time":13.33486709},
{"learn":[0.588628063],"iteration":202,"passed_time":3.391507297,"remaining_time":13.3154252},
{"learn":[0.5885448477],"iteration":203,"passed_time":3.408304165,"remaining_time":13.29906919},
{"learn":[0.5884083888],"iteration":204,"passed_time":3.424786043,"remaining_time":13.28148734},
{"learn":[0.5883219659],"iteration":205,"passed_time":3.441066632,"remaining_time":13.26314032},
{"learn":[0.5881961989],"iteration":206,"passed_time":3.456710313,"remaining_time":13.24237332},
{"learn":[0.5881137912],"iteration":207,"passed_time":3.471719924,"remaining_time":13.21924125},
{"learn":[0.5880295181],"iteration":208,"passed_time":3.488270406,"remaining_time":13.20201862},
{"learn":[0.5879345416],"iteration":209,"passed_time":3.508208614,"remaining_time":13.19754669},
{"learn":[0.5878083879],"iteration":210,"passed_time":3.52768971,"remaining_time":13.19121887},
{"learn":[0.5877102949],"iteration":211,"passed_time":3.54792813,"remaining_time":13.18758192},
{"learn":[0.5876309583],"iteration":212,"passed_time":3.566198634,"remaining_time":13.17651796},
{"learn":[0.5875334112],"iteration":213,"passed_time":3.585992121,"remaining_time":13.17098041},
{"learn":[0.5874344992],"iteration":214,"passed_time":3.605403182,"remaining_time":13.16391394},
{"learn":[0.5873156024],"iteration":215,"passed_time":3.623073244,"remaining_time":13.150414},
{"learn":[0.587165915],"iteration":216,"passed_time":3.642998078,"remaining_time":13.1450115},
{"learn":[0.587053058],"iteration":217,"passed_time":3.662613823,"remaining_time":13.13836702},
{"learn":[0.5869565573],"iteration":218,"passed_time":3.679617523,"remaining_time":13.12228897},
{"learn":[0.5868630937],"iteration":219,"passed_time":3.698404209,"remaining_time":13.11252401},
{"learn":[0.5867820396],"iteration":220,"passed_time":3.715816507,"remaining_time":13.09783285},
{"learn":[0.5866909191],"iteration":221,"passed_time":3.733738699,"remaining_time":13.08490409},
{"learn":[0.5866197493],"iteration":222,"passed_time":3.751957349,"remaining_time":13.0729635},
{"learn":[0.5865511274],"iteration":223,"passed_time":3.768674222,"remaining_time":13.05576427},
{"learn":[0.5864921283],"iteration":224,"passed_time":3.783664824,"remaining_time":13.03262328},
{"learn":[0.5863913509],"iteration":225,"passed_time":3.797460016,"remaining_time":13.00546041},
{"learn":[0.5862597147],"iteration":226,"passed_time":3.81142197,"remaining_time":12.97898318},
{"learn":[0.5861664558],"iteration":227,"passed_time":3.824877731,"remaining_time":12.95090179},
{"learn":[0.5860883135],"iteration":228,"passed_time":3.838842354,"remaining_time":12.92466138},
{"learn":[0.5859788119],"iteration":229,"passed_time":3.853486597,"remaining_time":12.90080295},
{"learn":[0.5858929464],"iteration":230,"passed_time":3.868091594,"remaining_time":12.87689366},
{"learn":[0.5858182278],"iteration":231,"passed_time":3.884348106,"remaining_time":12.85853166},
{"learn":[0.585685966],"iteration":232,"passed_time":3.899117517,"remaining_time":12.83529243},
{"learn":[0.5856033308],"iteration":233,"passed_time":3.913286344,"remaining_time":12.81015957},
{"learn":[0.5854758576],"iteration":234,"passed_time":3.92734824,"remaining_time":12.78477193},
{"learn":[0.5853802101],"iteration":235,"passed_time":3.941255557,"remaining_time":12.75897986},
{"learn":[0.5852991787],"iteration":236,"passed_time":3.955419516,"remaining_time":12.73411431},
{"learn":[0.5851900753],"iteration":237,"passed_time":3.96946652,"remaining_time":12.70896424},
{"learn":[0.5850623064],"iteration":238,"passed_time":3.981850974,"remaining_time":12.67861335},
{"learn":[0.5849861318],"iteration":239,"passed_time":3.995062451,"remaining_time":12.65103109},
{"learn":[0.5848821582],"iteration":240,"passed_time":4.008738974,"remaining_time":12.6250327},
{"learn":[0.5847932444],"iteration":241,"passed_time":4.023879997,"remaining_time":12.6037233},
{"learn":[0.5846862565],"iteration":242,"passed_time":4.039839535,"remaining_time":12.58501452},
{"learn":[0.5845688156],"iteration":243,"passed_time":4.055031218,"remaining_time":12.56394918},
{"learn":[0.5844836553],"iteration":244,"passed_time":4.06925835,"remaining_time":12.5399594},
{"learn":[0.5843937974],"iteration":245,"passed_time":4.083428652,"remaining_time":12.51587481},
{"learn":[0.5843100361],"iteration":246,"passed_time":4.097024868,"remaining_time":12.49012035},
{"learn":[0.5842146957],"iteration":247,"passed_time":4.111224102,"remaining_time":12.46629244},
{"learn":[0.5841210728],"iteration":248,"passed_time":4.125450048,"remaining_time":12.44262244},
{"learn":[0.5840450234],"iteration":249,"passed_time":4.139107167,"remaining_time":12.4173215},
{"learn":[0.5839555295],"iteration":250,"passed_time":4.153085432,"remaining_time":12.39307167},
{"learn":[0.5838911275],"iteration":251,"passed_time":4.166967556,"remaining_time":12.36861798},
{"learn":[0.5838093112],"iteration":252,"passed_time":4.180328241,"remaining_time":12.34270828},
{"learn":[0.583707294],"iteration":253,"passed_time":4.194177256,"remaining_time":12.31833163},
{"learn":[0.5835916503],"iteration":254,"passed_time":4.208275755,"remaining_time":12.29476642},
{"learn":[0.5835038056],"iteration":255,"passed_time":4.22225192,"remaining_time":12.27091964},
{"learn":[0.5834078737],"iteration":256,"passed_time":4.236160863,"remaining_time":12.24695533},
{"learn":[0.5833355779],"iteration":257,"passed_time":4.249948788,"remaining_time":12.22272093},
{"learn":[0.5832239265],"iteration":258,"passed_time":4.265123536,"remaining_time":12.2025349},
{"learn":[0.5831525407],"iteration":259,"passed_time":4.279172944,"remaining_time":12.17918453},
{"learn":[0.5830402751],"iteration":260,"passed_time":4.292900408,"remaining_time":12.15499388},
{"learn":[0.5829615186],"iteration":261,"passed_time":4.307378161,"remaining_time":12.1329965},
{"learn":[0.5828732758],"iteration":262,"passed_time":4.322082126,"remaining_time":12.11169022},
{"learn":[0.5827862046],"iteration":263,"passed_time":4.336697518,"remaining_time":12.09018702},
{"learn":[0.5826974727],"iteration":264,"passed_time":4.350564605,"remaining_time":12.06666032},
{"learn":[0.5826284186],"iteration":265,"passed_time":4.366928981,"remaining_time":12.05009726},
{"learn":[0.5825440545],"iteration":266,"passed_time":4.380397325,"remaining_time":12.02558517},
{"learn":[0.5824674364],"iteration":267,"passed_time":4.394920612,"remaining_time":12.0040369},
{"learn":[0.582378295],"iteration":268,"passed_time":4.409117082,"remaining_time":11.98165274},
{"learn":[0.5822707385],"iteration":269,"passed_time":4.423171285,"remaining_time":11.95894459},
{"learn":[0.5821941659],"iteration":270,"passed_time":4.436899676,"remaining_time":11.93542385},
{"learn":[0.582115671],"iteration":271,"passed_time":4.450987137,"remaining_time":11.91293616},
{"learn":[0.5820329903],"iteration":272,"passed_time":4.464806227,"remaining_time":11.88979534},
{"learn":[0.5819409712],"iteration":273,"passed_time":4.492159978,"remaining_time":11.90258447},
{"learn":[0.581826044],"iteration":274,"passed_time":4.510291973,"remaining_time":11.89076975},
{"learn":[0.5817536117],"iteration":275,"passed_time":4.524746637,"remaining_time":11.86926292},
{"learn":[0.5816561898],"iteration":276,"passed_time":4.539725038,"remaining_time":11.84917402},
{"learn":[0.5815696873],"iteration":277,"passed_time":4.555172124,"remaining_time":11.83033911},
{"learn":[0.5814696606],"iteration":278,"passed_time":4.571498681,"remaining_time":11.81380125},
{"learn":[0.5813684851],"iteration":279,"passed_time":4.589714665,"remaining_time":11.80212342},
{"learn":[0.5812563105],"iteration":280,"passed_time":4.608016885,"remaining_time":11.79061972},
{"learn":[0.5811812621],"iteration":281,"passed_time":4.628277497,"remaining_time":11.78405405},
{"learn":[0.5810990478],"iteration":282,"passed_time":4.649181604,"remaining_time":11.77902194},
{"learn":[0.5810125794],"iteration":283,"passed_time":4.667401657,"remaining_time":11.76711122},
{"learn":[0.5809282494],"iteration":284,"passed_time":4.687382266,"remaining_time":11.75957305},
{"learn":[0.5808461716],"iteration":285,"passed_time":4.708909573,"remaining_time":11.75580921},
{"learn":[0.5807711572],"iteration":286,"passed_time":4.728419709,"remaining_time":11.74691029},
{"learn":[0.5806485296],"iteration":287,"passed_time":4.746935633,"remaining_time":11.73547976},
{"learn":[0.5805420309],"iteration":288,"passed_time":4.777409878,"remaining_time":11.75342015},
{"learn":[0.5804539814],"iteration":289,"passed_time":4.806063522,"remaining_time":11.76656931},
{"learn":[0.5803927302],"iteration":290,"passed_time":4.826966213,"remaining_time":11.76054655},
{"learn":[0.5803009158],"iteration":291,"passed_time":4.848908607,"remaining_time":11.75694279},
{"learn":[0.5802480816],"iteration":292,"passed_time":4.872091072,"remaining_time":11.7562061},
{"learn":[0.5801426976],"iteration":293,"passed_time":4.894580436,"remaining_time":11.75365234},
{"learn":[0.5801002596],"iteration":294,"passed_time":4.916166557,"remaining_time":11.74880482},
{"learn":[0.579987687],"iteration":295,"passed_time":4.9383214,"remaining_time":11.74519684},
{"learn":[0.5798881721],"iteration":296,"passed_time":4.959052782,"remaining_time":11.73809463},
{"learn":[0.5798211427],"iteration":297,"passed_time":4.983186939,"remaining_time":11.73891688},
{"learn":[0.5797407141],"iteration":298,"passed_time":5.00185941,"remaining_time":11.72676738},
{"learn":[0.579652187],"iteration":299,"passed_time":5.024574593,"remaining_time":11.72400738},
{"learn":[0.5795881603],"iteration":300,"passed_time":5.044788867,"remaining_time":11.71530704},
{"learn":[0.5795418209],"iteration":301,"passed_time":5.06725935,"remaining_time":11.71174512},
{"learn":[0.5794726303],"iteration":302,"passed_time":5.089705282,"remaining_time":11.70800192},
{"learn":[0.5794053506],"iteration":303,"passed_time":5.111524488,"remaining_time":11.7027008},
{"learn":[0.5793275268],"iteration":304,"passed_time":5.134720662,"remaining_time":11.70042905},
{"learn":[0.5792432423],"iteration":305,"passed_time":5.154651182,"remaining_time":11.69061412},
{"learn":[0.5791655778],"iteration":306,"passed_time":5.177989099,"remaining_time":11.6884249},
{"learn":[0.5790795985],"iteration":307,"passed_time":5.202058721,"remaining_time":11.68774232},
{"learn":[0.578966605],"iteration":308,"passed_time":5.224615863,"remaining_time":11.68352609},
{"learn":[0.5788771679],"iteration":309,"passed_time":5.245751532,"remaining_time":11.6760276},
{"learn":[0.5788088645],"iteration":310,"passed_time":5.265814634,"remaining_time":11.66606522},
{"learn":[0.5787378994],"iteration":311,"passed_time":5.286490891,"remaining_time":11.65739017},
{"learn":[0.5786660813],"iteration":312,"passed_time":5.304818836,"remaining_time":11.64348415},
{"learn":[0.5784964887],"iteration":313,"passed_time":5.325619738,"remaining_time":11.63495268},
{"learn":[0.5783945511],"iteration":314,"passed_time":5.346264561,"remaining_time":11.62600389},
{"learn":[0.5783479273],"iteration":315,"passed_time":5.367962333,"remaining_time":11.61926024},
{"learn":[0.5782699215],"iteration":316,"passed_time":5.388713871,"remaining_time":11.61038351},
{"learn":[0.5782113205],"iteration":317,"passed_time":5.408678705,"remaining_time":11.5997449},
{"learn":[0.5781425621],"iteration":318,"passed_time":5.429225678,"remaining_time":11.59029055},
{"learn":[0.5780469601],"iteration":319,"passed_time":5.450375751,"remaining_time":11.58204847},
{"learn":[0.5779631761],"iteration":320,"passed_time":5.472038553,"remaining_time":11.57481052},
{"learn":[0.5779032101],"iteration":321,"passed_time":5.49197311,"remaining_time":11.563844},
{"learn":[0.5778365332],"iteration":322,"passed_time":5.511001572,"remaining_time":11.5509228},
{"learn":[0.5777674905],"iteration":323,"passed_time":5.53645598,"remaining_time":11.55137112},
{"learn":[0.5776717065],"iteration":324,"passed_time":5.553202382,"remaining_time":11.53357418},
{"learn":[0.5775960552],"iteration":325,"passed_time":5.575578034,"remaining_time":11.52742207},
{"learn":[0.5774971546],"iteration":326,"passed_time":5.598680632,"remaining_time":11.52266687},
{"learn":[0.5774328095],"iteration":327,"passed_time":5.619956038,"remaining_time":11.51405627},
{"learn":[0.5773653591],"iteration":328,"passed_time":5.640752311,"remaining_time":11.50439149},
{"learn":[0.5772821438],"iteration":329,"passed_time":5.661114217,"remaining_time":11.49377735},
{"learn":[0.5772132148],"iteration":330,"passed_time":5.681895288,"remaining_time":11.4839515},
{"learn":[0.5771449001],"iteration":331,"passed_time":5.702859445,"remaining_time":11.47442804},
{"learn":[0.5770575559],"iteration":332,"passed_time":5.719950891,"remaining_time":11.45707881},
{"learn":[0.5769778325],"iteration":333,"passed_time":5.740308167,"remaining_time":11.44624323},
{"learn":[0.5769039556],"iteration":334,"passed_time":5.761048285,"remaining_time":11.43611077},
{"learn":[0.5768115157],"iteration":335,"passed_time":5.781375894,"remaining_time":11.42509998},
{"learn":[0.5766762169],"iteration":336,"passed_time":5.801006086,"remaining_time":11.41266182},
{"learn":[0.5765853694],"iteration":337,"passed_time":5.821641343,"remaining_time":11.40214961},
{"learn":[0.5765051115],"iteration":338,"passed_time":5.84066277,"remaining_time":11.38843095},
{"learn":[0.5764461237],"iteration":339,"passed_time":5.860554252,"remaining_time":11.37637002},
{"learn":[0.5763772175],"iteration":340,"passed_time":5.879101968,"remaining_time":11.36166627},
{"learn":[0.5763060477],"iteration":341,"passed_time":5.89718312,"remaining_time":11.34604238},
{"learn":[0.5761855812],"iteration":342,"passed_time":5.919032626,"remaining_time":11.33762226},
{"learn":[0.5761039469],"iteration":343,"passed_time":5.939055433,"remaining_time":11.32564059},
{"learn":[0.5760294786],"iteration":344,"passed_time":5.957900445,"remaining_time":11.31137621},
{"learn":[0.5759742899],"iteration":345,"passed_time":5.977630518,"remaining_time":11.29875826},
{"learn":[0.5759005723],"iteration":346,"passed_time":5.994468081,"remaining_time":11.28065607},
{"learn":[0.5758368527],"iteration":347,"passed_time":6.014216749,"remaining_time":11.26801529},
{"learn":[0.5757634081],"iteration":348,"passed_time":6.036927222,"remaining_time":11.26085851},
{"learn":[0.5756638591],"iteration":349,"passed_time":6.057066211,"remaining_time":11.24883725},
{"learn":[0.5755911766],"iteration":350,"passed_time":6.075461171,"remaining_time":11.23354501},
{"learn":[0.5755165603],"iteration":351,"passed_time":6.094995426,"remaining_time":11.22033249},
{"learn":[0.5754397147],"iteration":352,"passed_time":6.113546154,"remaining_time":11.20528148},
{"learn":[0.5753700805],"iteration":353,"passed_time":6.132825047,"remaining_time":11.19153949},
{"learn":[0.5752919269],"iteration":354,"passed_time":6.149482794,"remaining_time":11.17300395},
{"learn":[0.5752212234],"iteration":355,"passed_time":6.169797378,"remaining_time":11.16109413},
{"learn":[0.5751524878],"iteration":356,"passed_time":6.189600977,"remaining_time":11.14821689},
{"learn":[0.5750861749],"iteration":357,"passed_time":6.213036743,"remaining_time":11.1418145},
{"learn":[0.5750010487],"iteration":358,"passed_time":6.231955523,"remaining_time":11.12725206},
{"learn":[0.5748964381],"iteration":359,"passed_time":6.255256085,"remaining_time":11.12045526},
{"learn":[0.5748184665],"iteration":360,"passed_time":6.275862954,"remaining_time":11.10879897},
{"learn":[0.5747406768],"iteration":361,"passed_time":6.296369722,"remaining_time":11.0969168},
{"learn":[0.5746474975],"iteration":362,"passed_time":6.319333868,"remaining_time":11.08929938},
{"learn":[0.5745855183],"iteration":363,"passed_time":6.338812821,"remaining_time":11.07550812},
{"learn":[0.574473685],"iteration":364,"passed_time":6.359718812,"remaining_time":11.06416834},
{"learn":[0.5744236034],"iteration":365,"passed_time":6.380059262,"remaining_time":11.05179665},
{"learn":[0.5743607711],"iteration":366,"passed_time":6.399800118,"remaining_time":11.03834734},
{"learn":[0.5742842439],"iteration":367,"passed_time":6.419111998,"remaining_time":11.02412713},
{"learn":[0.5741928732],"iteration":368,"passed_time":6.439019384,"remaining_time":11.01089765},
{"learn":[0.5741414949],"iteration":369,"passed_time":6.459936326,"remaining_time":10.99935104},
{"learn":[0.5740377147],"iteration":370,"passed_time":6.480940407,"remaining_time":10.98790166},
{"learn":[0.5739000728],"iteration":371,"passed_time":6.501720766,"remaining_time":10.97602323},
{"learn":[0.5738353296],"iteration":372,"passed_time":6.521851267,"remaining_time":10.96300468},
{"learn":[0.5737770243],"iteration":373,"passed_time":6.543663738,"remaining_time":10.95276337},
{"learn":[0.5737128384],"iteration":374,"passed_time":6.56342558,"remaining_time":10.93904263},
{"learn":[0.5736538051],"iteration":375,"passed_time":6.586038925,"remaining_time":10.93002205},
{"learn":[0.573570533],"iteration":376,"passed_time":6.60814918,"remaining_time":10.92009798},
{"learn":[0.5735220097],"iteration":377,"passed_time":6.631163176,"remaining_time":10.91159655},
{"learn":[0.5734505556],"iteration":378,"passed_time":6.652737533,"remaining_time":10.90065965},
{"learn":[0.573378237],"iteration":379,"passed_time":6.67536279,"remaining_time":10.89138139},
{"learn":[0.5733068852],"iteration":380,"passed_time":6.697367183,"remaining_time":10.88102437},
{"learn":[0.5732397534],"iteration":381,"passed_time":6.717584536,"remaining_time":10.8677153},
{"learn":[0.5731716206],"iteration":382,"passed_time":6.740234718,"remaining_time":10.85828935},
{"learn":[0.573099484],"iteration":383,"passed_time":6.762702622,"remaining_time":10.84850212},
{"learn":[0.5730090914],"iteration":384,"passed_time":6.785125526,"remaining_time":10.83857714},
{"learn":[0.572940788],"iteration":385,"passed_time":6.806943684,"remaining_time":10.82762545},
{"learn":[0.5728732467],"iteration":386,"passed_time":6.83019,"remaining_time":10.81887977},
{"learn":[0.5727982324],"iteration":387,"passed_time":6.85063064,"remaining_time":10.8056339},
{"learn":[0.5727504143],"iteration":388,"passed_time":6.875308448,"remaining_time":10.79900633},
{"learn":[0.5726789033],"iteration":389,"passed_time":6.896880885,"remaining_time":10.78742908},
{"learn":[0.5726259326],"iteration":390,"passed_time":6.920749915,"remaining_time":10.77937775},
{"learn":[0.5725661486],"iteration":391,"passed_time":6.94187138,"remaining_time":10.76698418},
{"learn":[0.5724941372],"iteration":392,"passed_time":6.966916238,"remaining_time":10.760606},
{"learn":[0.5724408139],"iteration":393,"passed_time":6.989906929,"remaining_time":10.7509736},
{"learn":[0.5723615341],"iteration":394,"passed_time":7.0122572,"remaining_time":10.74029267},
{"learn":[0.5723045028],"iteration":395,"passed_time":7.035539189,"remaining_time":10.73097391},
{"learn":[0.5722451397],"iteration":396,"passed_time":7.057483093,"remaining_time":10.71955241},
{"learn":[0.5721325329],"iteration":397,"passed_time":7.077860971,"remaining_time":10.70570931},
{"learn":[0.5720593043],"iteration":398,"passed_time":7.100875904,"remaining_time":10.69580556},
{"learn":[0.571996017],"iteration":399,"passed_time":7.124029553,"remaining_time":10.68604433},
{"learn":[0.5719551374],"iteration":400,"passed_time":7.147975452,"remaining_time":10.67739974},
{"learn":[0.5718925212],"iteration":401,"passed_time":7.170567438,"remaining_time":10.666665},
{"learn":[0.5718093059],"iteration":402,"passed_time":7.191830493,"remaining_time":10.65390274},
{"learn":[0.5717404224],"iteration":403,"passed_time":7.213229857,"remaining_time":10.64129949},
{"learn":[0.571669628],"iteration":404,"passed_time":7.235890361,"remaining_time":10.63050559},
{"learn":[0.5715881757],"iteration":405,"passed_time":7.262616599,"remaining_time":10.62560162},
{"learn":[0.5715140827],"iteration":406,"passed_time":7.283080038,"remaining_time":10.61146551},
{"learn":[0.5714366798],"iteration":407,"passed_time":7.304940272,"remaining_time":10.5993251},
{"learn":[0.5713000616],"iteration":408,"passed_time":7.329644335,"remaining_time":10.59124646},
{"learn":[0.5712205885],"iteration":409,"passed_time":7.348831701,"remaining_time":10.57514806},
{"learn":[0.5711533315],"iteration":410,"passed_time":7.37109717,"remaining_time":10.56344582},
{"learn":[0.5711122698],"iteration":411,"passed_time":7.393842603,"remaining_time":10.55237731},
{"learn":[0.5710462299],"iteration":412,"passed_time":7.415861045,"remaining_time":10.54021897},
{"learn":[0.5709619455],"iteration":413,"passed_time":7.438682549,"remaining_time":10.52914969},
{"learn":[0.5708882506],"iteration":414,"passed_time":7.461498729,"remaining_time":10.51801628},
{"learn":[0.5708152836],"iteration":415,"passed_time":7.483348629,"remaining_time":10.50547019},
{"learn":[0.5707628589],"iteration":416,"passed_time":7.507185128,"remaining_time":10.49565691},
{"learn":[0.5706892437],"iteration":417,"passed_time":7.532359216,"remaining_time":10.48763891},
{"learn":[0.5706065175],"iteration":418,"passed_time":7.553773654,"remaining_time":10.47432576},
{"learn":[0.5705572435],"iteration":419,"passed_time":7.575698192,"remaining_time":10.46167846},
{"learn":[0.5704949458],"iteration":420,"passed_time":7.596699698,"remaining_time":10.44771764},
{"learn":[0.5704277002],"iteration":421,"passed_time":7.618215907,"remaining_time":10.43442842},
{"learn":[0.5703578271],"iteration":422,"passed_time":7.639246155,"remaining_time":10.42043743},
{"learn":[0.5702377928],"iteration":423,"passed_time":7.662664408,"remaining_time":10.40965731},
{"learn":[0.5701622097],"iteration":424,"passed_time":7.682429989,"remaining_time":10.39387587},
{"learn":[0.5700830324],"iteration":425,"passed_time":7.70533047,"remaining_time":10.38229974},
{"learn":[0.5700122038],"iteration":426,"passed_time":7.726682908,"remaining_time":10.36859322},
{"learn":[0.5699593924],"iteration":427,"passed_time":7.749156271,"remaining_time":10.35634903},
{"learn":[0.5698925222],"iteration":428,"passed_time":7.772116112,"remaining_time":10.34470466},
{"learn":[0.5698052462],"iteration":429,"passed_time":7.794694218,"remaining_time":10.33250164},
{"learn":[0.5697375001],"iteration":430,"passed_time":7.816517352,"remaining_time":10.31925377},
{"learn":[0.5696851437],"iteration":431,"passed_time":7.83593091,"remaining_time":10.30279805},
{"learn":[0.569604954],"iteration":432,"passed_time":7.858251033,"remaining_time":10.29013472},
{"learn":[0.5695435207],"iteration":433,"passed_time":7.883487353,"remaining_time":10.28123005},
{"learn":[0.5694790846],"iteration":434,"passed_time":7.905192601,"remaining_time":10.26766395},
{"learn":[0.5694183907],"iteration":435,"passed_time":7.927733888,"remaining_time":10.255142},
{"learn":[0.5693395318],"iteration":436,"passed_time":7.949111753,"remaining_time":10.24107532},
{"learn":[0.5692600701],"iteration":437,"passed_time":7.967913915,"remaining_time":10.22367037},
{"learn":[0.5692025496],"iteration":438,"passed_time":7.989173682,"remaining_time":10.20939963},
{"learn":[0.5691360093],"iteration":439,"passed_time":8.009656743,"remaining_time":10.19410858},
{"learn":[0.5690742234],"iteration":440,"passed_time":8.032915965,"remaining_time":10.18231298},
{"learn":[0.5690019162],"iteration":441,"passed_time":8.054161866,"remaining_time":10.1679238},
{"learn":[0.5689218516],"iteration":442,"passed_time":8.073770766,"remaining_time":10.15144541},
{"learn":[0.5688575406],"iteration":443,"passed_time":8.094261077,"remaining_time":10.13605666},
{"learn":[0.5687851083],"iteration":444,"passed_time":8.116315562,"remaining_time":10.12259581},
{"learn":[0.5687249376],"iteration":445,"passed_time":8.137073839,"remaining_time":10.10748634},
{"learn":[0.5686684181],"iteration":446,"passed_time":8.15792705,"remaining_time":10.09246903},
{"learn":[0.5685938246],"iteration":447,"passed_time":8.17616205,"remaining_time":10.07419967},
{"learn":[0.5685269999],"iteration":448,"passed_time":8.19444765,"remaining_time":10.05599255},
{"learn":[0.5684708102],"iteration":449,"passed_time":8.213150189,"remaining_time":10.03829468},
{"learn":[0.568409286],"iteration":450,"passed_time":8.230527908,"remaining_time":10.01897965},
{"learn":[0.5683417674],"iteration":451,"passed_time":8.250793677,"remaining_time":10.00317464},
{"learn":[0.5682834848],"iteration":452,"passed_time":8.272609352,"remaining_time":9.989221447},
{"learn":[0.5682265786],"iteration":453,"passed_time":8.293204761,"remaining_time":9.973766078},
{"learn":[0.5681696496],"iteration":454,"passed_time":8.313004697,"remaining_time":9.957335296},
{"learn":[0.568097786],"iteration":455,"passed_time":8.331906742,"remaining_time":9.939818569},
{"learn":[0.5680431774],"iteration":456,"passed_time":8.350411228,"remaining_time":9.921823407},
{"learn":[0.5679639773],"iteration":457,"passed_time":8.370830887,"remaining_time":9.906092447},
{"learn":[0.567916],"iteration":458,"passed_time":8.389891512,"remaining_time":9.888739233},
{"learn":[0.5678435676],"iteration":459,"passed_time":8.408904083,"remaining_time":9.871322184},
{"learn":[0.5677662671],"iteration":460,"passed_time":8.429910006,"remaining_time":9.856228835},
{"learn":[0.5677100433],"iteration":461,"passed_time":8.449580988,"remaining_time":9.83955535},
{"learn":[0.5676436735],"iteration":462,"passed_time":8.468854357,"remaining_time":9.822407753},
{"learn":[0.5675722308],"iteration":463,"passed_time":8.487830283,"remaining_time":9.804907395},
{"learn":[0.5675192601],"iteration":464,"passed_time":8.507440998,"remaining_time":9.788131041},
{"learn":[0.5674417775],"iteration":465,"passed_time":8.527949811,"remaining_time":9.772371672},
{"learn":[0.5674006703],"iteration":466,"passed_time":8.545571472,"remaining_time":9.753296776},
{"learn":[0.5673296712],"iteration":467,"passed_time":8.565039694,"remaining_time":9.736327173},
{"learn":[0.5672423497],"iteration":468,"passed_time":8.586265562,"remaining_time":9.721336915},
{"learn":[0.5671716236],"iteration":469,"passed_time":8.606109579,"remaining_time":9.704761865},
{"learn":[0.5671044462],"iteration":470,"passed_time":8.62916742,"remaining_time":9.691782517},
{"learn":[0.567047267],"iteration":471,"passed_time":8.651141328,"remaining_time":9.677547926},
{"learn":[0.566969193],"iteration":472,"passed_time":8.671533257,"remaining_time":9.661518026},
{"learn":[0.5669150962],"iteration":473,"passed_time":8.693625395,"remaining_time":9.647356451},
{"learn":[0.5668541862],"iteration":474,"passed_time":8.715081933,"remaining_time":9.632458978},
{"learn":[0.5667940382],"iteration":475,"passed_time":8.733738162,"remaining_time":9.614451254},
{"learn":[0.5667320135],"iteration":476,"passed_time":8.756675843,"remaining_time":9.601135149},
{"learn":[0.5666766883],"iteration":477,"passed_time":8.778806956,"remaining_time":9.586897973},
{"learn":[0.5666199527],"iteration":478,"passed_time":8.798791238,"remaining_time":9.570292766},
{"learn":[0.5665563355],"iteration":479,"passed_time":8.819808223,"remaining_time":9.554792242},
{"learn":[0.5664989629],"iteration":480,"passed_time":8.84476355,"remaining_time":9.543518259},
{"learn":[0.5664377572],"iteration":481,"passed_time":8.863720714,"remaining_time":9.525741349},
{"learn":[0.5663972983],"iteration":482,"passed_time":8.883758172,"remaining_time":9.50911589},
{"learn":[0.5663598196],"iteration":483,"passed_time":8.90978594,"remaining_time":9.498862696},
{"learn":[0.5663108868],"iteration":484,"passed_time":8.935320363,"remaining_time":9.488020591},
{"learn":[0.5662554024],"iteration":485,"passed_time":8.957839804,"remaining_time":9.47392934},
{"learn":[0.5661968241],"iteration":486,"passed_time":8.980275175,"remaining_time":9.459714917},
{"learn":[0.5661416923],"iteration":487,"passed_time":9.002096221,"remaining_time":9.444822265},
{"learn":[0.5660656429],"iteration":488,"passed_time":9.02776886,"remaining_time":9.43392615},
{"learn":[0.5660184732],"iteration":489,"passed_time":9.05240576,"remaining_time":9.421891709},
{"learn":[0.5659480427],"iteration":490,"passed_time":9.07527892,"remaining_time":9.407977536},
{"learn":[0.5658816616],"iteration":491,"passed_time":9.09768101,"remaining_time":9.393540555},
{"learn":[0.5658117089],"iteration":492,"passed_time":9.118830648,"remaining_time":9.377783243},
{"learn":[0.5657293012],"iteration":493,"passed_time":9.138754897,"remaining_time":9.360748943},
{"learn":[0.565668266],"iteration":494,"passed_time":9.164983922,"remaining_time":9.350135112},
{"learn":[0.5656033408],"iteration":495,"passed_time":9.188890526,"remaining_time":9.337098437},
{"learn":[0.5655317502],"iteration":496,"passed_time":9.211526408,"remaining_time":9.322731958},
{"learn":[0.5654363529],"iteration":497,"passed_time":9.231707973,"remaining_time":9.305858238},
{"learn":[0.5653718599],"iteration":498,"passed_time":9.256484242,"remaining_time":9.293584379},
{"learn":[0.5653270333],"iteration":499,"passed_time":9.278678131,"remaining_time":9.278678131},
{"learn":[0.565266419],"iteration":500,"passed_time":9.298779489,"remaining_time":9.261658612},
{"learn":[0.5652116626],"iteration":501,"passed_time":9.323923362,"remaining_time":9.249629152},
{"learn":[0.5651503317],"iteration":502,"passed_time":9.34210646,"remaining_time":9.230669803},
{"learn":[0.5650458462],"iteration":503,"passed_time":9.362844784,"remaining_time":9.2142282},
{"learn":[0.5649666688],"iteration":504,"passed_time":9.384382934,"remaining_time":9.198553569},
{"learn":[0.5649050991],"iteration":505,"passed_time":9.405295237,"remaining_time":9.182244757},
{"learn":[0.5648625132],"iteration":506,"passed_time":9.425987859,"remaining_time":9.165704171},
{"learn":[0.5647920259],"iteration":507,"passed_time":9.449137374,"remaining_time":9.151526748},
{"learn":[0.5647307406],"iteration":508,"passed_time":9.468890701,"remaining_time":9.134037985},
{"learn":[0.5646312143],"iteration":509,"passed_time":9.490514299,"remaining_time":9.118337268},
{"learn":[0.564579802],"iteration":510,"passed_time":9.516052272,"remaining_time":9.10635922},
{"learn":[0.5645036161],"iteration":511,"passed_time":9.53736409,"remaining_time":9.090300148},
{"learn":[0.56443678],"iteration":512,"passed_time":9.558638087,"remaining_time":9.074184695},
{"learn":[0.5643808405],"iteration":513,"passed_time":9.5768204,"remaining_time":9.055125903},
{"learn":[0.5643361163],"iteration":514,"passed_time":9.595630184,"remaining_time":9.036661436},
{"learn":[0.5642789712],"iteration":515,"passed_time":9.615268393,"remaining_time":9.018972678},
{"learn":[0.5641876346],"iteration":516,"passed_time":9.636068525,"remaining_time":9.002361891},
{"learn":[0.5640630278],"iteration":517,"passed_time":9.657838267,"remaining_time":8.986637152},
{"learn":[0.5639850334],"iteration":518,"passed_time":9.677979446,"remaining_time":8.969379795},
{"learn":[0.5639218484],"iteration":519,"passed_time":9.697949759,"remaining_time":8.951953624},
{"learn":[0.5638806161],"iteration":520,"passed_time":9.717316415,"remaining_time":8.933962692},
{"learn":[0.5638326957],"iteration":521,"passed_time":9.736959103,"remaining_time":8.916219255},
{"learn":[0.5637484567],"iteration":522,"passed_time":9.758668616,"remaining_time":8.900353594},
{"learn":[0.5637003088],"iteration":523,"passed_time":9.780437217,"remaining_time":8.884519304},
{"learn":[0.5636402632],"iteration":524,"passed_time":9.80011884,"remaining_time":8.866774188},
{"learn":[0.5635629626],"iteration":525,"passed_time":9.82188662,"remaining_time":8.850901631},
{"learn":[0.5635263711],"iteration":526,"passed_time":9.8417931,"remaining_time":8.833336122},
{"learn":[0.5634506402],"iteration":527,"passed_time":9.860290319,"remaining_time":8.814501952},
{"learn":[0.5633844752],"iteration":528,"passed_time":9.88091361,"remaining_time":8.797562023},
{"learn":[0.5633320846],"iteration":529,"passed_time":9.899840219,"remaining_time":8.77910359},
{"learn":[0.563260221],"iteration":530,"passed_time":9.919010324,"remaining_time":8.760858459},
{"learn":[0.5631927479],"iteration":531,"passed_time":9.941439744,"remaining_time":8.745477068},
{"learn":[0.5631436331],"iteration":532,"passed_time":9.964622687,"remaining_time":8.730729447},
{"learn":[0.5630860217],"iteration":533,"passed_time":9.988231673,"remaining_time":8.716322022},
{"learn":[0.5630303552],"iteration":534,"passed_time":10.0092472,"remaining_time":8.699626069},
{"learn":[0.5629695248],"iteration":535,"passed_time":10.03103453,"remaining_time":8.683582133},
{"learn":[0.562905248],"iteration":536,"passed_time":10.05362159,"remaining_time":8.668206326},
{"learn":[0.5628234659],"iteration":537,"passed_time":10.07551215,"remaining_time":8.652205601},
{"learn":[0.5627575852],"iteration":538,"passed_time":10.09771609,"remaining_time":8.636451052},
{"learn":[0.5626930467],"iteration":539,"passed_time":10.11890247,"remaining_time":8.619805809},
{"learn":[0.5626219907],"iteration":540,"passed_time":10.14110262,"remaining_time":8.604003889},
{"learn":[0.5625685537],"iteration":541,"passed_time":10.1608234,"remaining_time":8.586083244},
{"learn":[0.5625128303],"iteration":542,"passed_time":10.18147074,"remaining_time":8.56893578},
{"learn":[0.5624436739],"iteration":543,"passed_time":10.2038465,"remaining_time":8.553224274},
{"learn":[0.562382343],"iteration":544,"passed_time":10.22482413,"remaining_time":8.536321061},
{"learn":[0.5623233097],"iteration":545,"passed_time":10.24520152,"remaining_time":8.518903829},
{"learn":[0.5622690196],"iteration":546,"passed_time":10.26610327,"remaining_time":8.501910017},
{"learn":[0.5622000906],"iteration":547,"passed_time":10.28592875,"remaining_time":8.484014226},
{"learn":[0.5621339142],"iteration":548,"passed_time":10.30277214,"remaining_time":8.463661628},
{"learn":[0.5620803748],"iteration":549,"passed_time":10.31798661,"remaining_time":8.441989042},
{"learn":[0.5620142552],"iteration":550,"passed_time":10.3341868,"remaining_time":8.421143147},
{"learn":[0.5619734666],"iteration":551,"passed_time":10.34814955,"remaining_time":8.398498186},
{"learn":[0.561909929],"iteration":552,"passed_time":10.36127646,"remaining_time":8.375209005},
{"learn":[0.5618393621],"iteration":553,"passed_time":10.37547586,"remaining_time":8.352819912},
{"learn":[0.5617702284],"iteration":554,"passed_time":10.38944031,"remaining_time":8.330271958},
{"learn":[0.56167325],"iteration":555,"passed_time":10.40224971,"remaining_time":8.306832502},
{"learn":[0.5616136139],"iteration":556,"passed_time":10.41690981,"remaining_time":8.284903137},
{"learn":[0.5615533409],"iteration":557,"passed_time":10.43105685,"remaining_time":8.262593418},
{"learn":[0.5614825237],"iteration":558,"passed_time":10.44527056,"remaining_time":8.240365507},
{"learn":[0.5614173369],"iteration":559,"passed_time":10.45891846,"remaining_time":8.217721644},
{"learn":[0.5613710657],"iteration":560,"passed_time":10.4728846,"remaining_time":8.195358897},
{"learn":[0.5612858485],"iteration":561,"passed_time":10.48579527,"remaining_time":8.172203433},
{"learn":[0.5612136437],"iteration":562,"passed_time":10.50290654,"remaining_time":8.15234486},
{"learn":[0.5611740152],"iteration":563,"passed_time":10.52031794,"remaining_time":8.132728053},
{"learn":[0.5611164151],"iteration":564,"passed_time":10.5340389,"remaining_time":8.110277738},
{"learn":[0.5610672662],"iteration":565,"passed_time":10.55036225,"remaining_time":8.08985374},
{"learn":[0.5610245553],"iteration":566,"passed_time":10.56565162,"remaining_time":8.068654588},
{"learn":[0.5609846197],"iteration":567,"passed_time":10.58128482,"remaining_time":8.047737751},
{"learn":[0.5609145419],"iteration":568,"passed_time":10.59569342,"remaining_time":8.025911888},
{"learn":[0.5608598423],"iteration":569,"passed_time":10.61285757,"remaining_time":8.0061908},
{"learn":[0.5608151976],"iteration":570,"passed_time":10.62881468,"remaining_time":7.985571797},
{"learn":[0.5607731123],"iteration":571,"passed_time":10.64271454,"remaining_time":7.963429759},
{"learn":[0.5606978705],"iteration":572,"passed_time":10.65743476,"remaining_time":7.941927823},
{"learn":[0.560638769],"iteration":573,"passed_time":10.67455684,"remaining_time":7.922232082},
{"learn":[0.5605318266],"iteration":574,"passed_time":10.69048964,"remaining_time":7.901666252},
{"learn":[0.5604842815],"iteration":575,"passed_time":10.7038589,"remaining_time":7.879229467},
{"learn":[0.5604096653],"iteration":576,"passed_time":10.71884793,"remaining_time":7.858011564},
{"learn":[0.5603516558],"iteration":577,"passed_time":10.73565397,"remaining_time":7.838141827},
{"learn":[0.560312141],"iteration":578,"passed_time":10.75028702,"remaining_time":7.816702649},
{"learn":[0.560246158],"iteration":579,"passed_time":10.76404793,"remaining_time":7.794655398},
{"learn":[0.5601831323],"iteration":580,"passed_time":10.78031519,"remaining_time":7.774444173},
{"learn":[0.5601156934],"iteration":581,"passed_time":10.79823173,"remaining_time":7.755431033},
{"learn":[0.5600519283],"iteration":582,"passed_time":10.81293009,"remaining_time":7.734119807},
{"learn":[0.5600049633],"iteration":583,"passed_time":10.82634155,"remaining_time":7.711914529},
{"learn":[0.5599467945],"iteration":584,"passed_time":10.84570893,"remaining_time":7.693964454},
{"learn":[0.5598805272],"iteration":585,"passed_time":10.86189413,"remaining_time":7.673761382},
{"learn":[0.5598177631],"iteration":586,"passed_time":10.8762037,"remaining_time":7.652252347},
{"learn":[0.55977189],"iteration":587,"passed_time":10.89439229,"remaining_time":7.633485751},
{"learn":[0.5597009819],"iteration":588,"passed_time":10.91029494,"remaining_time":7.613126014},
{"learn":[0.5596610008],"iteration":589,"passed_time":10.92651792,"remaining_time":7.593003976},
{"learn":[0.5596050045],"iteration":590,"passed_time":10.94597841,"remaining_time":7.575135647},
{"learn":[0.5595390897],"iteration":591,"passed_time":10.96574026,"remaining_time":7.557469636},
{"learn":[0.5594876546],"iteration":592,"passed_time":10.98412135,"remaining_time":7.538848887},
{"learn":[0.5594272678],"iteration":593,"passed_time":11.00414971,"remaining_time":7.52135485},
{"learn":[0.5593600222],"iteration":594,"passed_time":11.02230136,"remaining_time":7.502574872},
{"learn":[0.5592898875],"iteration":595,"passed_time":11.03924943,"remaining_time":7.48298116},
{"learn":[0.5592367575],"iteration":596,"passed_time":11.05710208,"remaining_time":7.464006933},
{"learn":[0.5591843783],"iteration":597,"passed_time":11.07554951,"remaining_time":7.445436292},
{"learn":[0.5591261299],"iteration":598,"passed_time":11.09407711,"remaining_time":7.426919734},
{"learn":[0.5590572236],"iteration":599,"passed_time":11.12758608,"remaining_time":7.418390722},
{"learn":[0.5589865316],"iteration":600,"passed_time":11.14230329,"remaining_time":7.39730285},
{"learn":[0.5589193429],"iteration":601,"passed_time":11.15404561,"remaining_time":7.374269355},
{"learn":[0.558850448],"iteration":602,"passed_time":11.17141279,"remaining_time":7.354976581},
{"learn":[0.5588117749],"iteration":603,"passed_time":11.18833768,"remaining_time":7.335400201},
{"learn":[0.5587609313],"iteration":604,"passed_time":11.20229771,"remaining_time":7.313896852},
{"learn":[0.5587194601],"iteration":605,"passed_time":11.21587579,"remaining_time":7.292170066},
{"learn":[0.5586619283],"iteration":606,"passed_time":11.23786171,"remaining_time":7.275913759},
{"learn":[0.5585927263],"iteration":607,"passed_time":11.25208407,"remaining_time":7.254633154},
{"learn":[0.5585497992],"iteration":608,"passed_time":11.26545406,"remaining_time":7.232828471},
{"learn":[0.5584776058],"iteration":609,"passed_time":11.27991756,"remaining_time":7.211750574},
{"learn":[0.5584320512],"iteration":610,"passed_time":11.29965786,"remaining_time":7.194053855},
{"learn":[0.5583655904],"iteration":611,"passed_time":11.31425962,"remaining_time":7.173092703},
{"learn":[0.5582890406],"iteration":612,"passed_time":11.32837486,"remaining_time":7.151845143},
{"learn":[0.5582341362],"iteration":613,"passed_time":11.34515753,"remaining_time":7.13229773},
{"learn":[0.5581351674],"iteration":614,"passed_time":11.36111494,"remaining_time":7.112242685},
{"learn":[0.5580961531],"iteration":615,"passed_time":11.37510851,"remaining_time":7.090976734},
{"learn":[0.558050371],"iteration":616,"passed_time":11.39035179,"remaining_time":7.070510107},
{"learn":[0.5579875615],"iteration":617,"passed_time":11.40446946,"remaining_time":7.049364617},
{"learn":[0.5579395159],"iteration":618,"passed_time":11.42085136,"remaining_time":7.029635487},
{"learn":[0.5578786741],"iteration":619,"passed_time":11.43518547,"remaining_time":7.008662059},
{"learn":[0.5578204598],"iteration":620,"passed_time":11.4501186,"remaining_time":6.988075606},
{"learn":[0.5577624389],"iteration":621,"passed_time":11.46412851,"remaining_time":6.966946264},
{"learn":[0.5576981165],"iteration":622,"passed_time":11.47760949,"remaining_time":6.945519709},
{"learn":[0.5576489335],"iteration":623,"passed_time":11.49195773,"remaining_time":6.924641194},
{"learn":[0.5575971571],"iteration":624,"passed_time":11.50671355,"remaining_time":6.904028127},
{"learn":[0.5575290926],"iteration":625,"passed_time":11.52141622,"remaining_time":6.883402022},
{"learn":[0.5574814679],"iteration":626,"passed_time":11.53605324,"remaining_time":6.862755758},
{"learn":[0.5574290545],"iteration":627,"passed_time":11.55074818,"remaining_time":6.842162937},
{"learn":[0.5573542222],"iteration":628,"passed_time":11.56469641,"remaining_time":6.821148438},
{"learn":[0.5573040155],"iteration":629,"passed_time":11.57977873,"remaining_time":6.800822431},
{"learn":[0.5572540249],"iteration":630,"passed_time":11.59450606,"remaining_time":6.780305446},
{"learn":[0.5571870523],"iteration":631,"passed_time":11.60776223,"remaining_time":6.75895016},
{"learn":[0.5571340702],"iteration":632,"passed_time":11.62269457,"remaining_time":6.73859227},
{"learn":[0.557084091],"iteration":633,"passed_time":11.63623428,"remaining_time":6.71744755},
{"learn":[0.5570176416],"iteration":634,"passed_time":11.65043649,"remaining_time":6.696707591},
{"learn":[0.5569493496],"iteration":635,"passed_time":11.66518355,"remaining_time":6.676300017},
{"learn":[0.5568936036],"iteration":636,"passed_time":11.67939778,"remaining_time":6.655606586},
{"learn":[0.5568315674],"iteration":637,"passed_time":11.69358927,"remaining_time":6.63492056},
{"learn":[0.5567618422],"iteration":638,"passed_time":11.70808726,"remaining_time":6.614428017},
{"learn":[0.5567002497],"iteration":639,"passed_time":11.72207645,"remaining_time":6.593668006},
{"learn":[0.5566503274],"iteration":640,"passed_time":11.74061885,"remaining_time":6.575479199},
{"learn":[0.5565922837],"iteration":641,"passed_time":11.75741825,"remaining_time":6.556317344},
{"learn":[0.5565310893],"iteration":642,"passed_time":11.77305402,"remaining_time":6.536516772},
{"learn":[0.5564969092],"iteration":643,"passed_time":11.78716597,"remaining_time":6.515886781},
{"learn":[0.5564416295],"iteration":644,"passed_time":11.80306772,"remaining_time":6.496262079},
{"learn":[0.5563962341],"iteration":645,"passed_time":11.81825025,"remaining_time":6.476254779},
{"learn":[0.5563463232],"iteration":646,"passed_time":11.83091769,"remaining_time":6.45489018},
{"learn":[0.5562752444],"iteration":647,"passed_time":11.84928415,"remaining_time":6.43664818},
{"learn":[0.556216723],"iteration":648,"passed_time":11.86675983,"remaining_time":6.417924036},
{"learn":[0.5561584063],"iteration":649,"passed_time":11.88527649,"remaining_time":6.399764262},
{"learn":[0.5560998849],"iteration":650,"passed_time":11.90532251,"remaining_time":6.382423279},
{"learn":[0.5560771133],"iteration":651,"passed_time":11.9227324,"remaining_time":6.363666984},
{"learn":[0.556031991],"iteration":652,"passed_time":11.94141341,"remaining_time":6.34559028},
{"learn":[0.5559768591],"iteration":653,"passed_time":11.95786376,"remaining_time":6.326331592},
{"learn":[0.5559284951],"iteration":654,"passed_time":11.97573593,"remaining_time":6.307830374},
{"learn":[0.5558669708],"iteration":655,"passed_time":11.99440405,"remaining_time":6.289748465},
{"learn":[0.5557851091],"iteration":656,"passed_time":12.01260453,"remaining_time":6.271420628},
{"learn":[0.5557215943],"iteration":657,"passed_time":12.03145205,"remaining_time":6.253429485},
{"learn":[0.5556494691],"iteration":658,"passed_time":12.0501931,"remaining_time":6.235380648},
{"learn":[0.5556120586],"iteration":659,"passed_time":12.06793057,"remaining_time":6.216812719},
{"learn":[0.5555676529],"iteration":660,"passed_time":12.08667384,"remaining_time":6.198763136},
{"learn":[0.5555155012],"iteration":661,"passed_time":12.10460359,"remaining_time":6.180296095},
{"learn":[0.5554615181],"iteration":662,"passed_time":12.12278033,"remaining_time":6.161956215},
{"learn":[0.5554064773],"iteration":663,"passed_time":12.13800177,"remaining_time":6.142121376},
{"learn":[0.5553536772],"iteration":664,"passed_time":12.15304725,"remaining_time":6.122211771},
{"learn":[0.5552971577],"iteration":665,"passed_time":12.16711176,"remaining_time":6.101824819},
{"learn":[0.5552009301],"iteration":666,"passed_time":12.18081051,"remaining_time":6.081274213},
{"learn":[0.5551497338],"iteration":667,"passed_time":12.19503239,"remaining_time":6.061004123},
{"learn":[0.5551046342],"iteration":668,"passed_time":12.2094487,"remaining_time":6.040848309},
{"learn":[0.5550504806],"iteration":669,"passed_time":12.2243921,"remaining_time":6.020969241},
{"learn":[0.555015436],"iteration":670,"passed_time":12.23863395,"remaining_time":6.00076091},
{"learn":[0.5549584388],"iteration":671,"passed_time":12.25174025,"remaining_time":5.980016077},
{"learn":[0.5548825486],"iteration":672,"passed_time":12.26620384,"remaining_time":5.959953428},
{"learn":[0.5548367211],"iteration":673,"passed_time":12.28030935,"remaining_time":5.939734197},
{"learn":[0.5547908821],"iteration":674,"passed_time":12.29420079,"remaining_time":5.919430011},
{"learn":[0.5547373996],"iteration":675,"passed_time":12.30844649,"remaining_time":5.89931459},
{"learn":[0.5546789919],"iteration":676,"passed_time":12.32315439,"remaining_time":5.879437027},
{"learn":[0.5546281596],"iteration":677,"passed_time":12.33723723,"remaining_time":5.859277856},
{"learn":[0.5545957198],"iteration":678,"passed_time":12.35101953,"remaining_time":5.838994504},
{"learn":[0.5545414638],"iteration":679,"passed_time":12.36608687,"remaining_time":5.819334999},
{"learn":[0.5544675187],"iteration":680,"passed_time":12.3805607,"remaining_time":5.799410961},
{"learn":[0.5544183015],"iteration":681,"passed_time":12.39552594,"remaining_time":5.779732036},
{"learn":[0.5543691071],"iteration":682,"passed_time":12.41686044,"remaining_time":5.763023076},
{"learn":[0.5543145554],"iteration":683,"passed_time":12.43285341,"remaining_time":5.743832863},
{"learn":[0.5542772814],"iteration":684,"passed_time":12.44969328,"remaining_time":5.725041434},
{"learn":[0.5542166444],"iteration":685,"passed_time":12.46499306,"remaining_time":5.705550757},
{"learn":[0.5541610917],"iteration":686,"passed_time":12.4823612,"remaining_time":5.687014638},
{"learn":[0.5541082802],"iteration":687,"passed_time":12.49757131,"remaining_time":5.66750327},
{"learn":[0.5540480413],"iteration":688,"passed_time":12.51249551,"remaining_time":5.64787533},
{"learn":[0.5539947749],"iteration":689,"passed_time":12.5276102,"remaining_time":5.628346613},
{"learn":[0.5539494705],"iteration":690,"passed_time":12.54354509,"remaining_time":5.609197445},
{"learn":[0.5538934174],"iteration":691,"passed_time":12.56057204,"remaining_time":5.590543627},
{"learn":[0.5538319841],"iteration":692,"passed_time":12.57639493,"remaining_time":5.571361101},
{"learn":[0.5537883632],"iteration":693,"passed_time":12.59102388,"remaining_time":5.551661825},
{"learn":[0.5537427404],"iteration":694,"passed_time":12.60803112,"remaining_time":5.533020849},
{"learn":[0.5537053413],"iteration":695,"passed_time":12.62346682,"remaining_time":5.513698152},
{"learn":[0.5536624597],"iteration":696,"passed_time":12.63826297,"remaining_time":5.494108582},
{"learn":[0.5536028464],"iteration":697,"passed_time":12.6559149,"remaining_time":5.475768337},
{"learn":[0.5535590548],"iteration":698,"passed_time":12.67213869,"remaining_time":5.456815086},
{"learn":[0.5535019893],"iteration":699,"passed_time":12.68618461,"remaining_time":5.43693626},
{"learn":[0.5534611438],"iteration":700,"passed_time":12.70161184,"remaining_time":5.417663251},
{"learn":[0.5534104594],"iteration":701,"passed_time":12.71880168,"remaining_time":5.399149431},
{"learn":[0.5533494697],"iteration":702,"passed_time":12.74501888,"remaining_time":5.384453211},
{"learn":[0.5533040061],"iteration":703,"passed_time":12.76298933,"remaining_time":5.366256878},
{"learn":[0.5532625805],"iteration":704,"passed_time":12.78428715,"remaining_time":5.34945349},
{"learn":[0.553209678],"iteration":705,"passed_time":12.81109746,"remaining_time":5.334932936},
{"learn":[0.5531649083],"iteration":706,"passed_time":12.82760242,"remaining_time":5.316106801},
{"learn":[0.553119422],"iteration":707,"passed_time":12.84672663,"remaining_time":5.29836748},
{"learn":[0.5530458636],"iteration":708,"passed_time":12.86313716,"remaining_time":5.279510455},
{"learn":[0.5530169953],"iteration":709,"passed_time":12.87968492,"remaining_time":5.260716377},
{"learn":[0.5529735678],"iteration":710,"passed_time":12.8933057,"remaining_time":5.240738883},
{"learn":[0.5529203923],"iteration":711,"passed_time":12.91022522,"remaining_time":5.222113574},
{"learn":[0.5528497458],"iteration":712,"passed_time":12.93016267,"remaining_time":5.204707836},
{"learn":[0.5528053628],"iteration":713,"passed_time":12.94483806,"remaining_time":5.185187232},
{"learn":[0.5527690897],"iteration":714,"passed_time":12.96038619,"remaining_time":5.166028062},
{"learn":[0.5527055295],"iteration":715,"passed_time":12.97862442,"remaining_time":5.147945999},
{"learn":[0.5526571313],"iteration":716,"passed_time":12.99406323,"remaining_time":5.12875857},
{"learn":[0.5526246004],"iteration":717,"passed_time":13.00752188,"remaining_time":5.108803859},
{"learn":[0.5525796601],"iteration":718,"passed_time":13.02526412,"remaining_time":5.090541332},
{"learn":[0.5525183861],"iteration":719,"passed_time":13.04156786,"remaining_time":5.071720833},
{"learn":[0.5524740486],"iteration":720,"passed_time":13.05688918,"remaining_time":5.05252716},
{"learn":[0.5524013433],"iteration":721,"passed_time":13.07447829,"remaining_time":5.034217401},
{"learn":[0.552335474],"iteration":722,"passed_time":13.09430469,"remaining_time":5.016766802},
{"learn":[0.5522858815],"iteration":723,"passed_time":13.11105337,"remaining_time":4.998136367},
{"learn":[0.5522219572],"iteration":724,"passed_time":13.12678616,"remaining_time":4.979125783},
{"learn":[0.5521407666],"iteration":725,"passed_time":13.1426212,"remaining_time":4.960162821},
{"learn":[0.5520928348],"iteration":726,"passed_time":13.1581949,"remaining_time":4.941110328},
{"learn":[0.552012247],"iteration":727,"passed_time":13.17417915,"remaining_time":4.922220782},
{"learn":[0.551957172],"iteration":728,"passed_time":13.18895616,"remaining_time":4.902890423},
{"learn":[0.5519197274],"iteration":729,"passed_time":13.20443851,"remaining_time":4.88383342},
{"learn":[0.5518536079],"iteration":730,"passed_time":13.21974939,"remaining_time":4.864723099},
{"learn":[0.5518147074],"iteration":731,"passed_time":13.23459763,"remaining_time":4.845453778},
{"learn":[0.5517533537],"iteration":732,"passed_time":13.25215321,"remaining_time":4.827182683},
{"learn":[0.551701748],"iteration":733,"passed_time":13.26779786,"remaining_time":4.808221023},
{"learn":[0.5516677612],"iteration":734,"passed_time":13.28231241,"remaining_time":4.788860936},
{"learn":[0.5516237877],"iteration":735,"passed_time":13.29649682,"remaining_time":4.769395599},
{"learn":[0.5515710786],"iteration":736,"passed_time":13.31436451,"remaining_time":4.751258977},
{"learn":[0.5515058576],"iteration":737,"passed_time":13.32981237,"remaining_time":4.732264011},
{"learn":[0.5514580851],"iteration":738,"passed_time":13.34480226,"remaining_time":4.713116899},
{"learn":[0.5514066272],"iteration":739,"passed_time":13.36152157,"remaining_time":4.69458866},
{"learn":[0.5513373569],"iteration":740,"passed_time":13.37671908,"remaining_time":4.675533391},
{"learn":[0.5512777208],"iteration":741,"passed_time":13.3908814,"remaining_time":4.656128574},
{"learn":[0.5512092923],"iteration":742,"passed_time":13.40579543,"remaining_time":4.63699788},
{"learn":[0.5511574477],"iteration":743,"passed_time":13.42245503,"remaining_time":4.61847915},
{"learn":[0.5511069339],"iteration":744,"passed_time":13.43544456,"remaining_time":4.598709211},
{"learn":[0.5510617774],"iteration":745,"passed_time":13.44922492,"remaining_time":4.579226717},
{"learn":[0.5510038361],"iteration":746,"passed_time":13.46432999,"remaining_time":4.56020815},
{"learn":[0.5509468161],"iteration":747,"passed_time":13.47779613,"remaining_time":4.540647894},
{"learn":[0.5509031497],"iteration":748,"passed_time":13.49171736,"remaining_time":4.521256418},
{"learn":[0.5508520444],"iteration":749,"passed_time":13.50574946,"remaining_time":4.501916486},
{"learn":[0.5507877903],"iteration":750,"passed_time":13.51996456,"remaining_time":4.482651366},
{"learn":[0.5507462395],"iteration":751,"passed_time":13.5339818,"remaining_time":4.463334425},
{"learn":[0.5506957826],"iteration":752,"passed_time":13.54880174,"remaining_time":4.44429486},
{"learn":[0.5506434944],"iteration":753,"passed_time":13.56308049,"remaining_time":4.42508992},
{"learn":[0.5506050488],"iteration":754,"passed_time":13.57716853,"remaining_time":4.405836145},
{"learn":[0.5505450146],"iteration":755,"passed_time":13.59126765,"remaining_time":4.386599613},
{"learn":[0.5505043283],"iteration":756,"passed_time":13.60534042,"remaining_time":4.367368194},
{"learn":[0.5504300419],"iteration":757,"passed_time":13.61956303,"remaining_time":4.348198224},
{"learn":[0.5503621935],"iteration":758,"passed_time":13.63383242,"remaining_time":4.329056145},
{"learn":[0.5503199944],"iteration":759,"passed_time":13.64855211,"remaining_time":4.310069088},
{"learn":[0.5502535791],"iteration":760,"passed_time":13.66201044,"remaining_time":4.290697103},
{"learn":[0.550204817],"iteration":761,"passed_time":13.67632247,"remaining_time":4.27160728},
{"learn":[0.5501505496],"iteration":762,"passed_time":13.69034491,"remaining_time":4.252440032},
{"learn":[0.5501142197],"iteration":763,"passed_time":13.70374557,"remaining_time":4.233094181},
{"learn":[0.5500620225],"iteration":764,"passed_time":13.73162333,"remaining_time":4.218211089},
{"learn":[0.5500091086],"iteration":765,"passed_time":13.74906772,"remaining_time":4.20010685},
{"learn":[0.549947391],"iteration":766,"passed_time":13.76340543,"remaining_time":4.18106058},
{"learn":[0.5499067616],"iteration":767,"passed_time":13.77903401,"remaining_time":4.162416523},
{"learn":[0.5498530402],"iteration":768,"passed_time":13.79423813,"remaining_time":4.143652806},
{"learn":[0.5497919368],"iteration":769,"passed_time":13.8114727,"remaining_time":4.125504834},
{"learn":[0.5497354741],"iteration":770,"passed_time":13.83009477,"remaining_time":4.10777134},
{"learn":[0.5496802968],"iteration":771,"passed_time":13.84489298,"remaining_time":4.088906218},
{"learn":[0.5496367783],"iteration":772,"passed_time":13.859232,"remaining_time":4.069916772},
{"learn":[0.5496015062],"iteration":773,"passed_time":13.87611317,"remaining_time":4.051681625},
{"learn":[0.5495538018],"iteration":774,"passed_time":13.89224037,"remaining_time":4.033231076},
{"learn":[0.549486033],"iteration":775,"passed_time":13.90568806,"remaining_time":4.014013047},
{"learn":[0.5494265334],"iteration":776,"passed_time":13.92265199,"remaining_time":3.995819038},
{"learn":[0.5493760196],"iteration":777,"passed_time":13.93660617,"remaining_time":3.976769369},
{"learn":[0.5493307721],"iteration":778,"passed_time":13.9507258,"remaining_time":3.95777972},
{"learn":[0.5492888688],"iteration":779,"passed_time":13.96451022,"remaining_time":3.93870801},
{"learn":[0.5492227037],"iteration":780,"passed_time":13.98181782,"remaining_time":3.920637776},
{"learn":[0.5491773539],"iteration":781,"passed_time":13.99750421,"remaining_time":3.902117542},
{"learn":[0.5491513292],"iteration":782,"passed_time":14.0144541,"remaining_time":3.883954714},
{"learn":[0.5490660324],"iteration":783,"passed_time":14.03211182,"remaining_time":3.865989992},
{"learn":[0.5489824077],"iteration":784,"passed_time":14.04860263,"remaining_time":3.847706452},
{"learn":[0.5489436436],"iteration":785,"passed_time":14.06573272,"remaining_time":3.829601531},
{"learn":[0.5488942218],"iteration":786,"passed_time":14.08034131,"remaining_time":3.810816645},
{"learn":[0.5488447203],"iteration":787,"passed_time":14.09487321,"remaining_time":3.792021726},
{"learn":[0.5487872567],"iteration":788,"passed_time":14.10898446,"remaining_time":3.773125122},
{"learn":[0.54873225],"iteration":789,"passed_time":14.12327034,"remaining_time":3.754287053},
{"learn":[0.5486684395],"iteration":790,"passed_time":14.13773741,"remaining_time":3.735508368},
{"learn":[0.5486294479],"iteration":791,"passed_time":14.15153832,"remaining_time":3.716565619},
{"learn":[0.5485739863],"iteration":792,"passed_time":14.16540298,"remaining_time":3.697652481},
{"learn":[0.5485231198],"iteration":793,"passed_time":14.17916419,"remaining_time":3.678725217},
{"learn":[0.5484600259],"iteration":794,"passed_time":14.19568644,"remaining_time":3.660522918},
{"learn":[0.5484034495],"iteration":795,"passed_time":14.21004941,"remaining_time":3.641771456},
{"learn":[0.5483433016],"iteration":796,"passed_time":14.22430635,"remaining_time":3.623004001},
{"learn":[0.5482748958],"iteration":797,"passed_time":14.23870267,"remaining_time":3.604283131},
{"learn":[0.5481952521],"iteration":798,"passed_time":14.2539696,"remaining_time":3.585792102},
{"learn":[0.5481305089],"iteration":799,"passed_time":14.26729215,"remaining_time":3.566823037},
{"learn":[0.5480942017],"iteration":800,"passed_time":14.28083618,"remaining_time":3.547923096},
{"learn":[0.5480411514],"iteration":801,"passed_time":14.29460949,"remaining_time":3.529093116},
{"learn":[0.5479905125],"iteration":802,"passed_time":14.31016015,"remaining_time":3.510711769},
{"learn":[0.5479620764],"iteration":803,"passed_time":14.32653725,"remaining_time":3.492538932},
{"learn":[0.5479249048],"iteration":804,"passed_time":14.34325919,"remaining_time":3.474454088},
{"learn":[0.5478865843],"iteration":805,"passed_time":14.35811712,"remaining_time":3.455923972},
{"learn":[0.5478486961],"iteration":806,"passed_time":14.37549997,"remaining_time":3.438006808},
{"learn":[0.5477988307],"iteration":807,"passed_time":14.39241088,"remaining_time":3.419978823},
{"learn":[0.5477386713],"iteration":808,"passed_time":14.40838964,"remaining_time":3.401733525},
{"learn":[0.5476921955],"iteration":809,"passed_time":14.42446061,"remaining_time":3.383515453},
{"learn":[0.5476370068],"iteration":810,"passed_time":14.43996351,"remaining_time":3.365170287},
{"learn":[0.5475611621],"iteration":811,"passed_time":14.45696741,"remaining_time":3.347179647},
{"learn":[0.5475107961],"iteration":812,"passed_time":14.47104593,"remaining_time":3.328518558},
{"learn":[0.5474728397],"iteration":813,"passed_time":14.48786448,"remaining_time":3.310494832},
{"learn":[0.5474323581],"iteration":814,"passed_time":14.50554124,"remaining_time":3.29266887},
{"learn":[0.5473806727],"iteration":815,"passed_time":14.52018499,"remaining_time":3.274159361},
{"learn":[0.5473374044],"iteration":816,"passed_time":14.53542451,"remaining_time":3.255792761},
{"learn":[0.5472820224],"iteration":817,"passed_time":14.55129001,"remaining_time":3.237573083},
{"learn":[0.5472326687],"iteration":818,"passed_time":14.56852209,"remaining_time":3.219661169},
{"learn":[0.5471802782],"iteration":819,"passed_time":14.58320397,"remaining_time":3.201191115},
{"learn":[0.5471374762],"iteration":820,"passed_time":14.60107193,"remaining_time":3.18342494},
{"learn":[0.5470824126],"iteration":821,"passed_time":14.61774503,"remaining_time":3.165399774},
{"learn":[0.5470204675],"iteration":822,"passed_time":14.63264575,"remaining_time":3.146996716},
{"learn":[0.5469612978],"iteration":823,"passed_time":14.64929872,"remaining_time":3.128976426},
{"learn":[0.5469184844],"iteration":824,"passed_time":14.66532293,"remaining_time":3.110826075},
{"learn":[0.5468641147],"iteration":825,"passed_time":14.68309014,"remaining_time":3.093048044},
{"learn":[0.5467760084],"iteration":826,"passed_time":14.69878154,"remaining_time":3.0748358},
{"learn":[0.5467300557],"iteration":827,"passed_time":14.71666871,"remaining_time":3.057085771},
{"learn":[0.5466808955],"iteration":828,"passed_time":14.73483242,"remaining_time":3.039392453},
{"learn":[0.5466249788],"iteration":829,"passed_time":14.74998886,"remaining_time":3.021082056},
{"learn":[0.5465779342],"iteration":830,"passed_time":14.76619685,"remaining_time":3.002993101},
{"learn":[0.5465268516],"iteration":831,"passed_time":14.78563761,"remaining_time":2.98556144},
{"learn":[0.5464824573],"iteration":832,"passed_time":14.80639139,"remaining_time":2.968388189},
{"learn":[0.5464142562],"iteration":833,"passed_time":14.82434163,"remaining_time":2.950648334},
{"learn":[0.5463541652],"iteration":834,"passed_time":14.84316455,"remaining_time":2.933080421},
{"learn":[0.5462806636],"iteration":835,"passed_time":14.8631244,"remaining_time":2.915732537},
{"learn":[0.5462255432],"iteration":836,"passed_time":14.88221916,"remaining_time":2.898209943},
{"learn":[0.5461611867],"iteration":837,"passed_time":14.90219121,"remaining_time":2.880853194},
{"learn":[0.5461149497],"iteration":838,"passed_time":14.92263511,"remaining_time":2.863580754},
{"learn":[0.5460796207],"iteration":839,"passed_time":14.94120489,"remaining_time":2.845943789},
{"learn":[0.5460217021],"iteration":840,"passed_time":14.95983457,"remaining_time":2.828315929},
{"learn":[0.5459792869],"iteration":841,"passed_time":14.97713757,"remaining_time":2.810436742},
{"learn":[0.5459258271],"iteration":842,"passed_time":14.99520846,"remaining_time":2.792701931},
{"learn":[0.5458690574],"iteration":843,"passed_time":15.01188101,"remaining_time":2.774707865},
{"learn":[0.5458338535],"iteration":844,"passed_time":15.03081547,"remaining_time":2.757131832},
{"learn":[0.5457841473],"iteration":845,"passed_time":15.05168163,"remaining_time":2.739904221},
{"learn":[0.5457285605],"iteration":846,"passed_time":15.06771698,"remaining_time":2.721795393},
{"learn":[0.5457035595],"iteration":847,"passed_time":15.08135802,"remaining_time":2.703262287},
{"learn":[0.5456630097],"iteration":848,"passed_time":15.09870346,"remaining_time":2.685399555},
{"learn":[0.545617057],"iteration":849,"passed_time":15.11665057,"remaining_time":2.667644219},
{"learn":[0.5455631991],"iteration":850,"passed_time":15.13085617,"remaining_time":2.649233337},
{"learn":[0.5455189185],"iteration":851,"passed_time":15.14754694,"remaining_time":2.631264022},
{"learn":[0.5454849658],"iteration":852,"passed_time":15.16369918,"remaining_time":2.613204899},
{"learn":[0.5454340425],"iteration":853,"passed_time":15.18034092,"remaining_time":2.595233927},
{"learn":[0.5453652955],"iteration":854,"passed_time":15.1966951,"remaining_time":2.577217298},
{"learn":[0.5453226301],"iteration":855,"passed_time":15.21188147,"remaining_time":2.559008097},
{"learn":[0.545259502],"iteration":856,"passed_time":15.22957575,"remaining_time":2.541224425},
{"learn":[0.545235047],"iteration":857,"passed_time":15.24353944,"remaining_time":2.522823544},
{"learn":[0.545212628],"iteration":858,"passed_time":15.26076515,"remaining_time":2.504968436},
{"learn":[0.5451753881],"iteration":859,"passed_time":15.27503511,"remaining_time":2.486633623},
{"learn":[0.5451272402],"iteration":860,"passed_time":15.29107676,"remaining_time":2.468594273},
{"learn":[0.5450742695],"iteration":861,"passed_time":15.3076053,"remaining_time":2.450637507},
{"learn":[0.5450253026],"iteration":862,"passed_time":15.32264043,"remaining_time":2.432446975},
{"learn":[0.5449592855],"iteration":863,"passed_time":15.33669368,"remaining_time":2.414109191},
{"learn":[0.544919293],"iteration":864,"passed_time":15.35097814,"remaining_time":2.395817398},
{"learn":[0.5448538218],"iteration":865,"passed_time":15.36488715,"remaining_time":2.377476764},
{"learn":[0.5447973706],"iteration":866,"passed_time":15.38015435,"remaining_time":2.359354704},
{"learn":[0.5447729838],"iteration":867,"passed_time":15.39418957,"remaining_time":2.341051869},
{"learn":[0.5446732415],"iteration":868,"passed_time":15.40974795,"remaining_time":2.322988471},
{"learn":[0.5446361381],"iteration":869,"passed_time":15.42374975,"remaining_time":2.304698238},
{"learn":[0.54460363],"iteration":870,"passed_time":15.43782931,"remaining_time":2.28642937},
{"learn":[0.5445644224],"iteration":871,"passed_time":15.45183463,"remaining_time":2.268159212},
{"learn":[0.5444994175],"iteration":872,"passed_time":15.46624335,"remaining_time":2.249957509},
{"learn":[0.5444173283],"iteration":873,"passed_time":15.48017247,"remaining_time":2.231695345},
{"learn":[0.5443774837],"iteration":874,"passed_time":15.49476965,"remaining_time":2.213538521},
{"learn":[0.5443289263],"iteration":875,"passed_time":15.50867199,"remaining_time":2.19529147},
{"learn":[0.5442895708],"iteration":876,"passed_time":15.52274981,"remaining_time":2.177078935},
{"learn":[0.5442526949],"iteration":877,"passed_time":15.53655374,"remaining_time":2.158837764},
{"learn":[0.544211474],"iteration":878,"passed_time":15.55069739,"remaining_time":2.140653452},
{"learn":[0.5441537829],"iteration":879,"passed_time":15.56499475,"remaining_time":2.122499284},
{"learn":[0.5441145867],"iteration":880,"passed_time":15.579326,"remaining_time":2.10435845},
{"learn":[0.5440687932],"iteration":881,"passed_time":15.59401043,"remaining_time":2.086273505},
{"learn":[0.544025832],"iteration":882,"passed_time":15.60939172,"remaining_time":2.068288597},
{"learn":[0.5439853505],"iteration":883,"passed_time":15.62332997,"remaining_time":2.050120223},
{"learn":[0.5439350755],"iteration":884,"passed_time":15.63749657,"remaining_time":2.03199108},
{"learn":[0.5438871778],"iteration":885,"passed_time":15.6520098,"remaining_time":2.013915482},
{"learn":[0.5438341616],"iteration":886,"passed_time":15.66819952,"remaining_time":1.996061495},
{"learn":[0.543788118],"iteration":887,"passed_time":15.68348623,"remaining_time":1.978097363},
{"learn":[0.5437337937],"iteration":888,"passed_time":15.69775263,"remaining_time":1.960011858},
{"learn":[0.5437001596],"iteration":889,"passed_time":15.71279598,"remaining_time":1.942030964},
{"learn":[0.5436633178],"iteration":890,"passed_time":15.72802316,"remaining_time":1.924079152},
{"learn":[0.5436149879],"iteration":891,"passed_time":15.74254033,"remaining_time":1.906047484},
{"learn":[0.5435732665],"iteration":892,"passed_time":15.75717667,"remaining_time":1.888037966},
{"learn":[0.543531602],"iteration":893,"passed_time":15.77244779,"remaining_time":1.870111259},
{"learn":[0.5434798711],"iteration":894,"passed_time":15.78703804,"remaining_time":1.852110608},
{"learn":[0.5434281061],"iteration":895,"passed_time":15.80480726,"remaining_time":1.834486557},
{"learn":[0.543372451],"iteration":896,"passed_time":15.82298428,"remaining_time":1.816909009},
{"learn":[0.5433251334],"iteration":897,"passed_time":15.84009747,"remaining_time":1.799209289},
{"learn":[0.5432770992],"iteration":898,"passed_time":15.85928082,"remaining_time":1.781743452},
{"learn":[0.5432351162],"iteration":899,"passed_time":15.87724337,"remaining_time":1.764138152},
{"learn":[0.5431700432],"iteration":900,"passed_time":15.89303485,"remaining_time":1.746293507},
{"learn":[0.5431223957],"iteration":901,"passed_time":15.90902758,"remaining_time":1.72847528},
{"learn":[0.543079298],"iteration":902,"passed_time":15.92742818,"remaining_time":1.71091975},
{"learn":[0.5430446515],"iteration":903,"passed_time":15.94119056,"remaining_time":1.692869794},
{"learn":[0.5429828429],"iteration":904,"passed_time":15.95571006,"remaining_time":1.674908791},
{"learn":[0.5429351955],"iteration":905,"passed_time":15.97194386,"remaining_time":1.657133249},
{"learn":[0.5428623081],"iteration":906,"passed_time":15.98701835,"remaining_time":1.639242234},
{"learn":[0.5428125678],"iteration":907,"passed_time":16.00561031,"remaining_time":1.62171382},
{"learn":[0.5427756009],"iteration":908,"passed_time":16.02269833,"remaining_time":1.604032506},
{"learn":[0.5427235402],"iteration":909,"passed_time":16.04156279,"remaining_time":1.586528188},
{"learn":[0.5426811477],"iteration":910,"passed_time":16.05652917,"remaining_time":1.568640062},
{"learn":[0.5426397903],"iteration":911,"passed_time":16.07184144,"remaining_time":1.550791717},
{"learn":[0.5425982395],"iteration":912,"passed_time":16.08587817,"remaining_time":1.532827383},
{"learn":[0.5425526508],"iteration":913,"passed_time":16.09883857,"remaining_time":1.514770368},
{"learn":[0.5425064821],"iteration":914,"passed_time":16.11406581,"remaining_time":1.496935075},
{"learn":[0.5424645104],"iteration":915,"passed_time":16.12876755,"remaining_time":1.479057286},
{"learn":[0.5424266109],"iteration":916,"passed_time":16.1435028,"remaining_time":1.461189458},
{"learn":[0.5424013141],"iteration":917,"passed_time":16.15771129,"remaining_time":1.4432814},
{"learn":[0.5423653027],"iteration":918,"passed_time":16.17209189,"remaining_time":1.425396565},
{"learn":[0.5423397558],"iteration":919,"passed_time":16.18588413,"remaining_time":1.407468185},
{"learn":[0.5422722258],"iteration":920,"passed_time":16.20034181,"remaining_time":1.389605866},
{"learn":[0.5422282068],"iteration":921,"passed_time":16.21487778,"remaining_time":1.371757556},
{"learn":[0.5421791603],"iteration":922,"passed_time":16.22895631,"remaining_time":1.353878262},
{"learn":[0.5421452417],"iteration":923,"passed_time":16.24291684,"remaining_time":1.335997489},
{"learn":[0.5420927715],"iteration":924,"passed_time":16.25757939,"remaining_time":1.318182113},
{"learn":[0.5420196226],"iteration":925,"passed_time":16.27166536,"remaining_time":1.30032747},
{"learn":[0.5419782993],"iteration":926,"passed_time":16.28884799,"remaining_time":1.282724815},
{"learn":[0.5419233381],"iteration":927,"passed_time":16.30493308,"remaining_time":1.265037911},
{"learn":[0.5418647143],"iteration":928,"passed_time":16.32192298,"remaining_time":1.247423608},
{"learn":[0.5418233797],"iteration":929,"passed_time":16.33753372,"remaining_time":1.229706839},
{"learn":[0.5417854801],"iteration":930,"passed_time":16.35191182,"remaining_time":1.211903239},
{"learn":[0.5417443388],"iteration":931,"passed_time":16.37094667,"remaining_time":1.194446753},
{"learn":[0.5417036866],"iteration":932,"passed_time":16.38595307,"remaining_time":1.176697595},
{"learn":[0.5416640354],"iteration":933,"passed_time":16.40093628,"remaining_time":1.15895267},
{"learn":[0.5416185036],"iteration":934,"passed_time":16.41841643,"remaining_time":1.141387239},
{"learn":[0.5415833907],"iteration":935,"passed_time":16.43468145,"remaining_time":1.123738902},
{"learn":[0.5415414987],"iteration":936,"passed_time":16.44937747,"remaining_time":1.105988027},
{"learn":[0.5414931119],"iteration":937,"passed_time":16.46395148,"remaining_time":1.088235599},
{"learn":[0.5414487858],"iteration":938,"passed_time":16.48211078,"remaining_time":1.070722852},
{"learn":[0.5414006947],"iteration":939,"passed_time":16.49715234,"remaining_time":1.053009724},
{"learn":[0.5413497942],"iteration":940,"passed_time":16.51378054,"remaining_time":1.035401755},
{"learn":[0.541308596],"iteration":941,"passed_time":16.52948483,"remaining_time":1.017738981},
{"learn":[0.5412637694],"iteration":942,"passed_time":16.54614362,"remaining_time":1.000138056},
{"learn":[0.541222412],"iteration":943,"passed_time":16.56013976,"remaining_time":0.9823811722},
{"learn":[0.5411634925],"iteration":944,"passed_time":16.57588227,"remaining_time":0.9647338887},
{"learn":[0.5411172782],"iteration":945,"passed_time":16.59371951,"remaining_time":0.9472102046},
{"learn":[0.5410913218],"iteration":946,"passed_time":16.60827742,"remaining_time":0.9295023268},
{"learn":[0.5410386923],"iteration":947,"passed_time":16.62470327,"remaining_time":0.9119035548},
{"learn":[0.5409907036],"iteration":948,"passed_time":16.64101838,"remaining_time":0.8943013039},
{"learn":[0.540951405],"iteration":949,"passed_time":16.65817621,"remaining_time":0.8767461166},
{"learn":[0.5409123452],"iteration":950,"passed_time":16.67348641,"remaining_time":0.859096566},
{"learn":[0.5408758333],"iteration":951,"passed_time":16.69161591,"remaining_time":0.8415940796},
{"learn":[0.5408276285],"iteration":952,"passed_time":16.70707208,"remaining_time":0.8239584341},
{"learn":[0.5407697327],"iteration":953,"passed_time":16.72162634,"remaining_time":0.8062838699},
{"learn":[0.5407322767],"iteration":954,"passed_time":16.73838208,"remaining_time":0.7887195743},
{"learn":[0.5406619032],"iteration":955,"passed_time":16.75657085,"remaining_time":0.7712229261},
{"learn":[0.5406138804],"iteration":956,"passed_time":16.77493709,"remaining_time":0.7537328055},
{"learn":[0.5405660509],"iteration":957,"passed_time":16.79046024,"remaining_time":0.7361162111},
{"learn":[0.5405227371],"iteration":958,"passed_time":16.80639765,"remaining_time":0.7185216933},
{"learn":[0.5404514991],"iteration":959,"passed_time":16.82322759,"remaining_time":0.7009678162},
{"learn":[0.5404055464],"iteration":960,"passed_time":16.83940017,"remaining_time":0.6833887686},
{"learn":[0.5403638137],"iteration":961,"passed_time":16.85834745,"remaining_time":0.6659222486},
{"learn":[0.5403128449],"iteration":962,"passed_time":16.87749447,"remaining_time":0.6484603275},
{"learn":[0.5402630135],"iteration":963,"passed_time":16.89677771,"remaining_time":0.6309999974},
{"learn":[0.5401769319],"iteration":964,"passed_time":16.91708845,"remaining_time":0.6135731562},
{"learn":[0.540134346],"iteration":965,"passed_time":16.93756946,"remaining_time":0.5961463371},
{"learn":[0.5400887005],"iteration":966,"passed_time":16.95499605,"remaining_time":0.5786089656},
{"learn":[0.5400316919],"iteration":967,"passed_time":16.97502309,"remaining_time":0.5611577879},
{"learn":[0.5399948615],"iteration":968,"passed_time":16.9939811,"remaining_time":0.5436670941},
{"learn":[0.5399458377],"iteration":969,"passed_time":17.01379922,"remaining_time":0.5261999758},
{"learn":[0.5399004424],"iteration":970,"passed_time":17.03260155,"remaining_time":0.5086976777},
{"learn":[0.5398508613],"iteration":971,"passed_time":17.04874379,"remaining_time":0.4911160763},
{"learn":[0.5397968669],"iteration":972,"passed_time":17.07008283,"remaining_time":0.4736816406},
{"learn":[0.5397589673],"iteration":973,"passed_time":17.08453159,"remaining_time":0.4560552582},
{"learn":[0.5397144592],"iteration":974,"passed_time":17.0994958,"remaining_time":0.4384486102},
{"learn":[0.5396826108],"iteration":975,"passed_time":17.11579069,"remaining_time":0.4208800988},
{"learn":[0.539628025],"iteration":976,"passed_time":17.13130725,"remaining_time":0.4032958718},
{"learn":[0.5395541367],"iteration":977,"passed_time":17.14750965,"remaining_time":0.3857313009},
{"learn":[0.5395182618],"iteration":978,"passed_time":17.16375379,"remaining_time":0.3681704082},
{"learn":[0.5394758352],"iteration":979,"passed_time":17.17994883,"remaining_time":0.3506112005},
{"learn":[0.5394193498],"iteration":980,"passed_time":17.19478013,"remaining_time":0.3330283614},
{"learn":[0.5393595317],"iteration":981,"passed_time":17.21019046,"remaining_time":0.3154617396},
{"learn":[0.5393105989],"iteration":982,"passed_time":17.22883668,"remaining_time":0.2979554664},
{"learn":[0.5392711183],"iteration":983,"passed_time":17.24353506,"remaining_time":0.280382684},
{"learn":[0.539222686],"iteration":984,"passed_time":17.25705631,"remaining_time":0.2627978118},
{"learn":[0.5391523466],"iteration":985,"passed_time":17.27497157,"remaining_time":0.2452835721},
{"learn":[0.5391154479],"iteration":986,"passed_time":17.29170739,"remaining_time":0.2277529849},
{"learn":[0.5390792545],"iteration":987,"passed_time":17.30508596,"remaining_time":0.2101832302},
{"learn":[0.5390436185],"iteration":988,"passed_time":17.31970503,"remaining_time":0.1926357485},
{"learn":[0.5389850288],"iteration":989,"passed_time":17.33199512,"remaining_time":0.1750706578},
{"learn":[0.5389319102],"iteration":990,"passed_time":17.34604641,"remaining_time":0.1575322076},
{"learn":[0.5388795538],"iteration":991,"passed_time":17.36109594,"remaining_time":0.1400088382},
{"learn":[0.5388419841],"iteration":992,"passed_time":17.37642335,"remaining_time":0.1224924103},
{"learn":[0.5387906513],"iteration":993,"passed_time":17.39135931,"remaining_time":0.104978024},
{"learn":[0.5387480427],"iteration":994,"passed_time":17.40766512,"remaining_time":0.08747570413},
{"learn":[0.5387064919],"iteration":995,"passed_time":17.42381437,"remaining_time":0.06997515811},
{"learn":[0.538628725],"iteration":996,"passed_time":17.43855838,"remaining_time":0.05247309444},
{"learn":[0.5385985031],"iteration":997,"passed_time":17.45252722,"remaining_time":0.03497500445},
{"learn":[0.538571068],"iteration":998,"passed_time":17.46663195,"remaining_time":0.01748411607},
{"learn":[0.5385407324],"iteration":999,"passed_time":17.48100446,"remaining_time":0}
]}